01_Módulo_Básico/Circuitos_Digitais_II/Aulas_06e07/count_sync_pwm_0/Quartus/rtl/structural/pwm_50hz_struct.v
// ============================================================================
// Arquivo  : pwm_50hz_struct  (implementação Structural)
// Autor    : Manoel Furtado
// Data     : 27/11/2025
// Ferramentas: Compatível com Quartus e Questa (Verilog 2001)
// Descrição: Implementação estrutural da geração de PWM a 50 Hz. O módulo
//            principal instancia três blocos: um contador síncrono, um
//            seletor de limiar de duty cycle e um comparador. Cada bloco
//            é descrito como submódulo separado, evidenciando a composição
//            hierárquica do circuito. Essa abordagem facilita a reutilização
//            de componentes e a verificação modular, ao custo de maior
//            verbosidade na descrição. A largura do contador e dos limiares
//            é parametrizável para acomodar diferentes frequências de clock.
// Revisão   : v1.0 — criação inicial
// ============================================================================

`timescale 1ns/1ps

// --------------------------------------------------------------------------
// Módulo top-level estrutural do PWM de 50 Hz
// --------------------------------------------------------------------------
module pwm_50hz_struct
#(
    // Frequência do clock de entrada em Hz
    parameter integer CLK_FREQ_HZ = 100_000_000,
    // Frequência desejada do PWM em Hz
    parameter integer PWM_FREQ_HZ = 50,
    // Número de ciclos de clock para completar um período de PWM
    parameter integer COUNTER_MAX = CLK_FREQ_HZ / PWM_FREQ_HZ
)
(
    input  wire        clk,       // Clock de 100 MHz
    input  wire        reset_n,   // Reset assíncrono ativo em nível baixo
    input  wire [1:0]  duty_sel,  // Seleção de duty cycle
    output wire        pwm_out    // Saída PWM estrutural
);

    // Sinal interno do contador
    wire [31:0] counter;
    // Limiar selecionado para o duty cycle
    wire [31:0] threshold;
    // Sinal PWM intermediário vindo do comparador
    wire        pwm_raw;

    // Instância do contador síncrono parametrizável
    pwm_counter_struct
    #(
        .COUNTER_MAX (COUNTER_MAX)
    ) u_counter (
        .clk      (clk),
        .reset_n  (reset_n),
        .count_q  (counter)
    );

    // Instância do seletor de limiar de duty cycle
    pwm_duty_selector_struct
    #(
        .COUNTER_MAX (COUNTER_MAX)
    ) u_duty_selector (
        .duty_sel  (duty_sel),
        .threshold (threshold)
    );

    // Instância do comparador PWM
    pwm_comparator_struct u_comparator (
        .counter   (counter),
        .threshold (threshold),
        .pwm_raw   (pwm_raw)
    );

    // Tratamento do caso especial de 100% e 0% na saída final
    assign pwm_out =
        (duty_sel == 2'b10) ? 1'b1 :  // 100% em nível alto
        (duty_sel == 2'b11) ? 1'b0 :  // 0% em nível alto
                              pwm_raw; // Casos 30% e 60% usam comparador

endmodule

// --------------------------------------------------------------------------
// Submódulo: pwm_counter_struct
// Contador síncrono parametrizável
// --------------------------------------------------------------------------
module pwm_counter_struct
#(
    parameter integer COUNTER_MAX = 2_000_000
)
(
    input  wire       clk,      // Clock de 100 MHz
    input  wire       reset_n,  // Reset assíncrono ativo em nível baixo
    output reg [31:0] count_q   // Saída do valor atual do contador
);

    // Bloco sequencial do contador
    always @(posedge clk or negedge reset_n) begin
        if (!reset_n) begin
            count_q <= 32'd0;                // Zera contador no reset
        end else begin
            if (count_q >= (COUNTER_MAX - 1)) begin
                count_q <= 32'd0;            // Reinicia quando atinge limite
            end else begin
                count_q <= count_q + 32'd1;  // Incrementa contador
            end
        end
    end

endmodule

// --------------------------------------------------------------------------
// Submódulo: pwm_duty_selector_struct
// Seleciona limiar de duty cycle com base em duty_sel
// --------------------------------------------------------------------------
module pwm_duty_selector_struct
#(
    parameter integer COUNTER_MAX = 2_000_000
)
(
    input  wire [1:0]  duty_sel,   // Seleção de duty cycle
    output reg  [31:0] threshold   // Limiar correspondente
);

    // Cálculo local dos limiares de 30%, 60% e 100%
    localparam integer DUTY_30  = (COUNTER_MAX * 30) / 100;
    localparam integer DUTY_60  = (COUNTER_MAX * 60) / 100;
    localparam integer DUTY_100 = COUNTER_MAX;

    // Lógica combinacional de seleção do limiar
    always @* begin
        case (duty_sel)
            2'b00: threshold = DUTY_30;   // 30%
            2'b01: threshold = DUTY_60;   // 60%
            2'b10: threshold = DUTY_100;  // 100%
            default: threshold = 32'd0;   // 0%
        endcase
    end

endmodule

// --------------------------------------------------------------------------
// Submódulo: pwm_comparator_struct
// Compara contador com limiar para gerar PWM bruto
// --------------------------------------------------------------------------
module pwm_comparator_struct
(
    input  wire [31:0] counter,    // Valor atual do contador
    input  wire [31:0] threshold,  // Limiar de duty cycle
    output wire        pwm_raw     // Saída PWM bruta
);

    // Saída em nível alto enquanto contador for menor que o limiar
    assign pwm_raw = (counter < threshold) ? 1'b1 : 1'b0;

endmodule

01_Módulo_Básico/Circuitos_Digitais_II/Aulas_06e07/count_sync_pwm_0/Quartus/rtl/dataflow/pwm_50hz_data.v
// ============================================================================
// Arquivo  : pwm_50hz_data  (implementação Dataflow)
// Autor    : Manoel Furtado
// Data     : 27/11/2025
// Ferramentas: Compatível com Quartus e Questa (Verilog 2001)
// Descrição: Implementação em estilo dataflow da geração de PWM a 50 Hz.
//            O contador permanece sequencial, mas toda a lógica de seleção
//            de duty cycle e comparação é realizada por meio de atribuições
//            contínuas (assign). Esta abordagem facilita a visualização das
//            relações combinacionais entre sinais, destacando o papel do
//            comparador e da seleção de limiar. Cuidados incluem evitar
//            dependência em valores não inicializados e garantir que o
//            contador seja dimensionado para o maior valor de COUNTER_MAX.
// Revisão   : v1.0 — criação inicial
// ============================================================================

`timescale 1ns/1ps

module pwm_50hz_data
#(
    // Frequência do clock de entrada em Hz
    parameter integer CLK_FREQ_HZ = 100_000_000,
    // Frequência desejada do PWM em Hz
    parameter integer PWM_FREQ_HZ = 50,
    // Número de ciclos de clock para completar um período de PWM
    parameter integer COUNTER_MAX = CLK_FREQ_HZ / PWM_FREQ_HZ
)
(
    input  wire        clk,       // Clock de 100 MHz
    input  wire        reset_n,   // Reset assíncrono ativo em nível baixo
    input  wire [1:0]  duty_sel,  // Seleção de duty cycle: 00=30%, 01=60%, 10=100%, 11=0%
    output wire        pwm_out    // Saída PWM em estilo dataflow
);

    // Limite de contador correspondente a 30% do período
    localparam integer DUTY_30  = (COUNTER_MAX * 30) / 100;
    // Limite de contador correspondente a 60% do período
    localparam integer DUTY_60  = (COUNTER_MAX * 60) / 100;
    // Limite de contador correspondente a 100% do período
    localparam integer DUTY_100 = COUNTER_MAX;

    // Registrador de contador
    reg [31:0] counter;

    // Limiar de comparação selecionado conforme entrada duty_sel
    wire [31:0] threshold;
    // Sinal intermediário indicando se o contador está abaixo do limiar
    wire        below_threshold;
    // Sinal bruto de PWM antes do tratamento do caso de 100%
    wire        pwm_raw;

    // Contador síncrono responsável por gerar a rampa temporal
    always @(posedge clk or negedge reset_n) begin
        if (!reset_n) begin
            counter <= 32'd0;        // Zera o contador no reset
        end else begin
            if (counter >= (COUNTER_MAX - 1)) begin
                counter <= 32'd0;    // Reinicia contador ao final do período
            end else begin
                counter <= counter + 32'd1; // Incrementa contador
            end
        end
    end

    // Seleção do limiar de comparação em função de duty_sel
    assign threshold =
        (duty_sel == 2'b00) ? DUTY_30  :   // 30%
        (duty_sel == 2'b01) ? DUTY_60  :   // 60%
        (duty_sel == 2'b10) ? DUTY_100 :   // 100%
                               32'd0;      // 0% (caso default)

    // Comparador: verifica se o contador está abaixo do limiar escolhido
    assign below_threshold = (counter < threshold) ? 1'b1 : 1'b0;

    // Saída PWM bruta baseada no comparador
    assign pwm_raw = below_threshold;

    // Tratamento explícito do caso de 100% para evitar glitches
    assign pwm_out =
        (duty_sel == 2'b10) ? 1'b1 :  // 100% do tempo em nível alto
        (duty_sel == 2'b11) ? 1'b0 :  // 0% do tempo em nível alto
                              pwm_raw; // Demais casos utilizam comparador

endmodule

01_Módulo_Básico/Circuitos_Digitais_II/Aulas_06e07/count_sync_pwm_0/Questa/rtl/behavioral/pwm_50hz_behav.v
// ============================================================================
// Arquivo  : pwm_50hz_behav  (implementação Behavioral)
// Autor    : Manoel Furtado
// Data     : 27/11/2025
// Ferramentas: Compatível com Quartus e Questa (Verilog 2001)
// Descrição: Módulo de geração de PWM a 50 Hz com seleção de duty cycle via
//            entrada de 2 bits. Implementação em estilo behavioral, utilizando
//            um contador síncrono e lógica sequencial dentro de um único bloco
//            always sensível à borda de subida do clock. O parâmetro
//            COUNTER_MAX define o número de ciclos do clock de 100 MHz para
//            compor um período de 50 Hz. Os limites de comparação para 30%,
//            60% e 100% de duty cycle são calculados com base em COUNTER_MAX.
//            Cuidados de síntese incluem o uso de largura suficiente para o
//            contador (32 bits) e reset assíncrono ativo em nível baixo para
//            garantir inicialização conhecida do circuito.
// Revisão   : v1.0 — criação inicial
// ============================================================================

`timescale 1ns/1ps

module pwm_50hz_behav
#(
    // Frequência do clock de entrada em Hz
    parameter integer CLK_FREQ_HZ = 100_000_000,
    // Frequência desejada do PWM em Hz
    parameter integer PWM_FREQ_HZ = 50,
    // Número de ciclos de clock para completar um período de PWM
    parameter integer COUNTER_MAX = CLK_FREQ_HZ / PWM_FREQ_HZ
)
(
    input  wire        clk,       // Clock de 100 MHz
    input  wire        reset_n,   // Reset assíncrono ativo em nível baixo
    input  wire [1:0]  duty_sel,  // Seleção de duty cycle: 00=30%, 01=60%, 10=100%, 11=0%
    output reg         pwm_out    // Saída PWM conectada (teoricamente) a um LED
);

    // Limite de contador correspondente a 30% do período
    localparam integer DUTY_30  = (COUNTER_MAX * 30) / 100;
    // Limite de contador correspondente a 60% do período
    localparam integer DUTY_60  = (COUNTER_MAX * 60) / 100;
    // Limite de contador correspondente a 100% do período (sempre alto)
    localparam integer DUTY_100 = COUNTER_MAX;

    // Registrador de contador com largura suficiente para COUNTER_MAX
    reg [31:0] counter;

    // Bloco sequencial: apenas o contador
    always @(posedge clk or negedge reset_n) begin
        if (!reset_n) begin
            counter <= 32'd0;
        end else begin
            if (counter >= (COUNTER_MAX - 1)) begin
                counter <= 32'd0;
            end else begin
                counter <= counter + 32'd1;
            end
        end
    end

    // Bloco combinacional: saída PWM
    always @* begin
        case (duty_sel)
            2'b00: begin
                // Duty cycle de aproximadamente 30%
                pwm_out = (counter < DUTY_30) ? 1'b1 : 1'b0;
            end
            2'b01: begin
                // Duty cycle de aproximadamente 60%
                pwm_out = (counter < DUTY_60) ? 1'b1 : 1'b0;
            end
            2'b10: begin
                // Duty cycle de 100%
                pwm_out = 1'b1;
            end
            default: begin
                // Caso reservado: 0%
                pwm_out = 1'b0;
            end
        endcase
    end

endmodule

01_Módulo_Básico/Circuitos_Digitais_II/Aulas_06e07/count_sync_pwm_0/Questa/tb/tb_pwm_50hz.v
// ============================================================================
// Arquivo  : tb_pwm_50hz
// Autor    : Manoel Furtado
// Data     : 27/11/2025
// Ferramentas: Compatível com Quartus e Questa (Verilog 2001)
// Descrição: Testbench unificado para as três implementações do módulo
//            pwm_50hz (behavioral, dataflow e structural). Nesta versão,
//            o valor de COUNTER_MAX é REDUZIDO apenas para simulação, de
//            modo a evitar tempos de simulação excessivamente longos.
//            As DUTs continuam parametrizáveis para síntese real.
// Revisão   : v1.1 — redução de COUNTER_MAX no testbench
// ============================================================================

`timescale 1ns/1ps

module tb_pwm_50hz;

    // ---------------------------------------------------------------------
    // Parâmetros de configuração GENERICOS
    // ---------------------------------------------------------------------
    // Frequência do clock de entrada em Hz (mantida para referência)
    localparam integer CLK_FREQ_HZ     = 100_000_000;
    // Frequência desejada do PWM em Hz (conceitual)
    localparam integer PWM_FREQ_HZ     = 50;

    // *** IMPORTANTE ***
    // Para uma síntese real, COUNTER_MAX deveria ser CLK_FREQ_HZ / PWM_FREQ_HZ
    // = 2_000_000 ciclos. Isso torna a simulação muito lenta.
    // Aqui, usamos um valor REDUZIDO apenas no testbench para acelerar a simulação.
    localparam integer TB_COUNTER_MAX  = 2000;  // valor reduzido para simulação

    // Período do clock em nanosegundos (10 ns para 100 MHz)
    localparam real    CLK_PERIOD_NS   = 10.0;

    // ---------------------------------------------------------------------
    // Sinais do testbench
    // ---------------------------------------------------------------------
    reg         clk;          // Clock de 100 MHz
    reg         reset_n;      // Reset assíncrono ativo em nível baixo
    reg  [1:0]  duty_sel;     // Seleção de duty cycle
    wire        pwm_behav;    // Saída da implementação behavioral
    wire        pwm_data;     // Saída da implementação dataflow
    wire        pwm_struct;   // Saída da implementação structural

    // Contadores auxiliares para avaliação numérica
    integer     high_behav;   // Contagem de ciclos em nível alto (behavioral)
    integer     high_data;    // Contagem de ciclos em nível alto (dataflow)
    integer     high_struct;  // Contagem de ciclos em nível alto (structural)
    integer     total_cycles; // Número total de ciclos avaliados
    integer     total_tests;  // Número acumulado de ciclos testados
    integer     error_flag;   // Indicador de inconsistência entre abordagens
    integer     i;            // Índice genérico de laços

    // ---------------------------------------------------------------------
    // Instâncias das três DUTs com COUNTER_MAX reduzido APENAS para simulação
    // ---------------------------------------------------------------------
    pwm_50hz_behav #(
        .CLK_FREQ_HZ (CLK_FREQ_HZ),
        .PWM_FREQ_HZ (PWM_FREQ_HZ),
        .COUNTER_MAX (TB_COUNTER_MAX)
    ) u_pwm_behav (
        .clk      (clk),
        .reset_n  (reset_n),
        .duty_sel (duty_sel),
        .pwm_out  (pwm_behav)
    );

    pwm_50hz_data #(
        .CLK_FREQ_HZ (CLK_FREQ_HZ),
        .PWM_FREQ_HZ (PWM_FREQ_HZ),
        .COUNTER_MAX (TB_COUNTER_MAX)
    ) u_pwm_data (
        .clk      (clk),
        .reset_n  (reset_n),
        .duty_sel (duty_sel),
        .pwm_out  (pwm_data)
    );

    pwm_50hz_struct #(
        .CLK_FREQ_HZ (CLK_FREQ_HZ),
        .PWM_FREQ_HZ (PWM_FREQ_HZ),
        .COUNTER_MAX (TB_COUNTER_MAX)
    ) u_pwm_struct (
        .clk      (clk),
        .reset_n  (reset_n),
        .duty_sel (duty_sel),
        .pwm_out  (pwm_struct)
    );

    // ---------------------------------------------------------------------
    // Geração do clock de 100 MHz (período de 10 ns)
    // ---------------------------------------------------------------------
    initial begin
        clk = 1'b0;                           // Inicializa clock em 0
        forever #(CLK_PERIOD_NS/2.0) clk = ~clk; // Inverte clock a cada 5 ns
    end

    // ---------------------------------------------------------------------
    // Geração de arquivo de ondas (VCD)
    // ---------------------------------------------------------------------
    initial begin
        $dumpfile("wave.vcd");                // Nome do arquivo de ondas
        $dumpvars(0, tb_pwm_50hz);            // Salva todos os sinais do TB
    end

    // ---------------------------------------------------------------------
    // Tarefa: executa uma medição completa para um duty_sel específico
    // ---------------------------------------------------------------------
    task automatic run_case;
        input [1:0] duty_sel_in;              // Valor de entrada de duty_sel
        input integer expected_percent;       // Duty cycle esperado em %
        integer meas_behav;                   // Duty medido (behavioral)
        integer meas_data;                    // Duty medido (dataflow)
        integer meas_struct;                  // Duty medido (structural)
        integer cycle;                        // Índice de ciclos
    begin
        // Aplica seleção de duty cycle
        duty_sel = duty_sel_in;

        // Aguarda um período completo para estabilização após mudança
        repeat (TB_COUNTER_MAX) @(posedge clk);

        // Zera contadores para nova janela de medição
        high_behav   = 0;
        high_data    = 0;
        high_struct  = 0;
        total_cycles = 0;

        // Mede o duty cycle efetivo ao longo de um período
        for (cycle = 0; cycle < TB_COUNTER_MAX; cycle = cycle + 1) begin
                @(posedge clk);
            total_cycles = total_cycles + 1;

            // Contadores de ciclos em nível alto
            if (pwm_behav)   high_behav  = high_behav  + 1;
            if (pwm_data)    high_data   = high_data   + 1;
            if (pwm_struct)  high_struct = high_struct + 1;

            // Comparação automática das três implementações
            if ((pwm_behav !== pwm_data) || (pwm_behav !== pwm_struct)) begin
                $display("ERRO: implementacoes divergentes em t=%0t ns. behav=%b data=%b struct=%b",
                         $time, pwm_behav, pwm_data, pwm_struct);
                error_flag = 1;
            end
        end

        // Acumula número total de testes realizados
        total_tests = total_tests + total_cycles;

        // Cálculo aproximado do duty cycle em porcentagem
        meas_behav  = (high_behav  * 100) / total_cycles;
        meas_data   = (high_data   * 100) / total_cycles;
        meas_struct = (high_struct * 100) / total_cycles;

        // Impressão de resumo numérico da medição
        $display("Resumo DUTY esperado = %0d%%", expected_percent);
        $display("  Behavioral: %0d%% (high=%0d de %0d ciclos)",
                 meas_behav, high_behav, total_cycles);
        $display("  Dataflow  : %0d%% (high=%0d de %0d ciclos)",
                 meas_data,  high_data,  total_cycles);
        $display("  Structural: %0d%% (high=%0d de %0d ciclos)",
                 meas_struct, high_struct, total_cycles);
        $display("----------------------------------------------------");

    end
    endtask

    // ---------------------------------------------------------------------
    // Tabela didática baseada na implementação behavioral
    // Mostra os primeiros 16 ciclos após mudança de duty_sel
    // ---------------------------------------------------------------------
    task automatic tabela_didatica;
        input [1:0] duty_sel_in; // Valor de duty_sel usado na tabela
        integer k;               // Índice de ciclos
    begin
        duty_sel = duty_sel_in;  // Aplica seleção de duty

        // Aguarda borda de clock para alinhar a observação
        @(posedge clk);

        $display("Tabela didatica (baseada em pwm_behav):");
        $display("linha | tempo(ns) | duty_sel | pwm_behav");
        $display("------+-----------+----------+----------");

        // Captura 16 amostras sequenciais
        for (k = 0; k < 16; k = k + 1) begin
            @(posedge clk);
            $display("%4d | %9t |    %b    |     %b",
                     k, $time, duty_sel, pwm_behav);
        end

        $display("====================================================");
    end
    endtask

    // ---------------------------------------------------------------------
    // Bloco principal de estímulos
    // ---------------------------------------------------------------------
    initial begin
        // Inicialização dos sinais
        reset_n     = 1'b0;      // Aplica reset
        duty_sel    = 2'b00;     // Duty inicial de 30%
        error_flag  = 0;         // Nenhum erro no início
        total_tests = 0;         // Zera contador de testes

        // Mantém reset ativo por alguns ciclos
        repeat (5) @(posedge clk);
        reset_n = 1'b1;          // Libera reset

        // Executa casos de teste para 30%, 60% e 100%
        run_case(2'b00, 30);     // Caso duty = 30%
        tabela_didatica(2'b00);  // Tabela didática para duty 30%

        run_case(2'b01, 60);     // Caso duty = 60%
        tabela_didatica(2'b01);  // Tabela didática para duty 60%

        run_case(2'b10, 100);    // Caso duty = 100%
        tabela_didatica(2'b10);  // Tabela didática para duty 100%

        // Mensagem final de sucesso ou falha
        if (error_flag == 0) begin
            $display("SUCESSO: Todas as implementacoes estao consistentes em %0d testes.",
                     total_tests);
        end else begin
            $display("FALHA: Foram detectadas divergencias entre as implementacoes.");
        end

        // Finalização da simulação
        $display("Fim da simulacao.");
        $finish;
    end

endmodule

01_Módulo_Básico/Circuitos_Digitais_II/Aulas_06e07/count_sync_pwm_0/Questa/scripts/wave.vcd
$date
	Thu Nov 27 13:58:31 2025
$end
$version
	Questa Intel Starter FPGA Edition Version 2024.3
$end
$timescale
	1ps
$end

$scope module tb_pwm_50hz $end
$var parameter 32 ! CLK_FREQ_HZ $end
$var parameter 32 " PWM_FREQ_HZ $end
$var parameter 32 # TB_COUNTER_MAX $end
$var parameter 0 $ CLK_PERIOD_NS $end
$var reg 1 % clk $end
$var reg 1 & reset_n $end
$var reg 2 ' duty_sel [1:0] $end
$var wire 1 ( pwm_behav $end
$var wire 1 ) pwm_data $end
$var wire 1 * pwm_struct $end
$var integer 32 + high_behav $end
$var integer 32 , high_data $end
$var integer 32 - high_struct $end
$var integer 32 . total_cycles $end
$var integer 32 / total_tests $end
$var integer 32 0 error_flag $end
$var integer 32 1 i $end

$scope task run_case $end
$upscope $end

$scope task tabela_didatica $end
$upscope $end

$scope module u_pwm_behav $end
$var parameter 32 2 CLK_FREQ_HZ $end
$var parameter 32 3 PWM_FREQ_HZ $end
$var parameter 32 4 COUNTER_MAX $end
$var parameter 32 5 DUTY_30 $end
$var parameter 32 6 DUTY_60 $end
$var parameter 32 7 DUTY_100 $end
$var wire 1 8 clk $end
$var wire 1 9 reset_n $end
$var wire 1 : duty_sel [1] $end
$var wire 1 ; duty_sel [0] $end
$var reg 1 < pwm_out $end
$var reg 32 = counter [31:0] $end
$upscope $end

$scope module u_pwm_data $end
$var parameter 32 > CLK_FREQ_HZ $end
$var parameter 32 ? PWM_FREQ_HZ $end
$var parameter 32 @ COUNTER_MAX $end
$var parameter 32 A DUTY_30 $end
$var parameter 32 B DUTY_60 $end
$var parameter 32 C DUTY_100 $end
$var wire 1 D clk $end
$var wire 1 E reset_n $end
$var wire 1 F duty_sel [1] $end
$var wire 1 G duty_sel [0] $end
$var wire 1 ) pwm_out $end
$var reg 32 H counter [31:0] $end
$var wire 1 I threshold [31] $end
$var wire 1 J threshold [30] $end
$var wire 1 K threshold [29] $end
$var wire 1 L threshold [28] $end
$var wire 1 M threshold [27] $end
$var wire 1 N threshold [26] $end
$var wire 1 O threshold [25] $end
$var wire 1 P threshold [24] $end
$var wire 1 Q threshold [23] $end
$var wire 1 R threshold [22] $end
$var wire 1 S threshold [21] $end
$var wire 1 T threshold [20] $end
$var wire 1 U threshold [19] $end
$var wire 1 V threshold [18] $end
$var wire 1 W threshold [17] $end
$var wire 1 X threshold [16] $end
$var wire 1 Y threshold [15] $end
$var wire 1 Z threshold [14] $end
$var wire 1 [ threshold [13] $end
$var wire 1 \ threshold [12] $end
$var wire 1 ] threshold [11] $end
$var wire 1 ^ threshold [10] $end
$var wire 1 _ threshold [9] $end
$var wire 1 ` threshold [8] $end
$var wire 1 a threshold [7] $end
$var wire 1 b threshold [6] $end
$var wire 1 c threshold [5] $end
$var wire 1 d threshold [4] $end
$var wire 1 e threshold [3] $end
$var wire 1 f threshold [2] $end
$var wire 1 g threshold [1] $end
$var wire 1 h threshold [0] $end
$var wire 1 i below_threshold $end
$var wire 1 j pwm_raw $end
$upscope $end

$scope module u_pwm_struct $end
$var parameter 32 k CLK_FREQ_HZ $end
$var parameter 32 l PWM_FREQ_HZ $end
$var parameter 32 m COUNTER_MAX $end
$var wire 1 n clk $end
$var wire 1 o reset_n $end
$var wire 1 p duty_sel [1] $end
$var wire 1 q duty_sel [0] $end
$var wire 1 * pwm_out $end
$var wire 1 r counter [31] $end
$var wire 1 s counter [30] $end
$var wire 1 t counter [29] $end
$var wire 1 u counter [28] $end
$var wire 1 v counter [27] $end
$var wire 1 w counter [26] $end
$var wire 1 x counter [25] $end
$var wire 1 y counter [24] $end
$var wire 1 z counter [23] $end
$var wire 1 { counter [22] $end
$var wire 1 | counter [21] $end
$var wire 1 } counter [20] $end
$var wire 1 ~ counter [19] $end
$var wire 1 !! counter [18] $end
$var wire 1 "! counter [17] $end
$var wire 1 #! counter [16] $end
$var wire 1 $! counter [15] $end
$var wire 1 %! counter [14] $end
$var wire 1 &! counter [13] $end
$var wire 1 '! counter [12] $end
$var wire 1 (! counter [11] $end
$var wire 1 )! counter [10] $end
$var wire 1 *! counter [9] $end
$var wire 1 +! counter [8] $end
$var wire 1 ,! counter [7] $end
$var wire 1 -! counter [6] $end
$var wire 1 .! counter [5] $end
$var wire 1 /! counter [4] $end
$var wire 1 0! counter [3] $end
$var wire 1 1! counter [2] $end
$var wire 1 2! counter [1] $end
$var wire 1 3! counter [0] $end
$var wire 1 4! threshold [31] $end
$var wire 1 5! threshold [30] $end
$var wire 1 6! threshold [29] $end
$var wire 1 7! threshold [28] $end
$var wire 1 8! threshold [27] $end
$var wire 1 9! threshold [26] $end
$var wire 1 :! threshold [25] $end
$var wire 1 ;! threshold [24] $end
$var wire 1 <! threshold [23] $end
$var wire 1 =! threshold [22] $end
$var wire 1 >! threshold [21] $end
$var wire 1 ?! threshold [20] $end
$var wire 1 @! threshold [19] $end
$var wire 1 A! threshold [18] $end
$var wire 1 B! threshold [17] $end
$var wire 1 C! threshold [16] $end
$var wire 1 D! threshold [15] $end
$var wire 1 E! threshold [14] $end
$var wire 1 F! threshold [13] $end
$var wire 1 G! threshold [12] $end
$var wire 1 H! threshold [11] $end
$var wire 1 I! threshold [10] $end
$var wire 1 J! threshold [9] $end
$var wire 1 K! threshold [8] $end
$var wire 1 L! threshold [7] $end
$var wire 1 M! threshold [6] $end
$var wire 1 N! threshold [5] $end
$var wire 1 O! threshold [4] $end
$var wire 1 P! threshold [3] $end
$var wire 1 Q! threshold [2] $end
$var wire 1 R! threshold [1] $end
$var wire 1 S! threshold [0] $end
$var wire 1 T! pwm_raw $end

$scope module u_counter $end
$var parameter 32 U! COUNTER_MAX $end
$var wire 1 n clk $end
$var wire 1 o reset_n $end
$var reg 32 V! count_q [31:0] $end
$upscope $end

$scope module u_duty_selector $end
$var parameter 32 W! COUNTER_MAX $end
$var parameter 32 X! DUTY_30 $end
$var parameter 32 Y! DUTY_60 $end
$var parameter 32 Z! DUTY_100 $end
$var wire 1 p duty_sel [1] $end
$var wire 1 q duty_sel [0] $end
$var reg 32 [! threshold [31:0] $end
$upscope $end

$scope module u_comparator $end
$var wire 1 r counter [31] $end
$var wire 1 s counter [30] $end
$var wire 1 t counter [29] $end
$var wire 1 u counter [28] $end
$var wire 1 v counter [27] $end
$var wire 1 w counter [26] $end
$var wire 1 x counter [25] $end
$var wire 1 y counter [24] $end
$var wire 1 z counter [23] $end
$var wire 1 { counter [22] $end
$var wire 1 | counter [21] $end
$var wire 1 } counter [20] $end
$var wire 1 ~ counter [19] $end
$var wire 1 !! counter [18] $end
$var wire 1 "! counter [17] $end
$var wire 1 #! counter [16] $end
$var wire 1 $! counter [15] $end
$var wire 1 %! counter [14] $end
$var wire 1 &! counter [13] $end
$var wire 1 '! counter [12] $end
$var wire 1 (! counter [11] $end
$var wire 1 )! counter [10] $end
$var wire 1 *! counter [9] $end
$var wire 1 +! counter [8] $end
$var wire 1 ,! counter [7] $end
$var wire 1 -! counter [6] $end
$var wire 1 .! counter [5] $end
$var wire 1 /! counter [4] $end
$var wire 1 0! counter [3] $end
$var wire 1 1! counter [2] $end
$var wire 1 2! counter [1] $end
$var wire 1 3! counter [0] $end
$var wire 1 4! threshold [31] $end
$var wire 1 5! threshold [30] $end
$var wire 1 6! threshold [29] $end
$var wire 1 7! threshold [28] $end
$var wire 1 8! threshold [27] $end
$var wire 1 9! threshold [26] $end
$var wire 1 :! threshold [25] $end
$var wire 1 ;! threshold [24] $end
$var wire 1 <! threshold [23] $end
$var wire 1 =! threshold [22] $end
$var wire 1 >! threshold [21] $end
$var wire 1 ?! threshold [20] $end
$var wire 1 @! threshold [19] $end
$var wire 1 A! threshold [18] $end
$var wire 1 B! threshold [17] $end
$var wire 1 C! threshold [16] $end
$var wire 1 D! threshold [15] $end
$var wire 1 E! threshold [14] $end
$var wire 1 F! threshold [13] $end
$var wire 1 G! threshold [12] $end
$var wire 1 H! threshold [11] $end
$var wire 1 I! threshold [10] $end
$var wire 1 J! threshold [9] $end
$var wire 1 K! threshold [8] $end
$var wire 1 L! threshold [7] $end
$var wire 1 M! threshold [6] $end
$var wire 1 N! threshold [5] $end
$var wire 1 O! threshold [4] $end
$var wire 1 P! threshold [3] $end
$var wire 1 Q! threshold [2] $end
$var wire 1 R! threshold [1] $end
$var wire 1 S! threshold [0] $end
$var wire 1 T! pwm_raw $end
$upscope $end
$upscope $end
$upscope $end
$enddefinitions $end
#0
$dumpvars
0%
0&
b0 '
1<
b0 =
b0 H
b0 V!
b1001011000 [!
b101111101011110000100000000 !
b110010 "
b11111010000 #
b101111101011110000100000000 2
b110010 3
b11111010000 4
b1001011000 5
b10010110000 6
b11111010000 7
b101111101011110000100000000 >
b110010 ?
b11111010000 @
b1001011000 A
b10010110000 B
b11111010000 C
b101111101011110000100000000 k
b110010 l
b11111010000 m
b11111010000 U!
b11111010000 W!
b1001011000 X!
b10010110000 Y!
b11111010000 Z!
r10 $
bx +
bx ,
bx -
bx .
b0 /
b0 0
bx 1
1(
1)
1*
0h
0g
0f
1e
1d
0c
1b
0a
0`
1_
0^
0]
0\
0[
0Z
0Y
0X
0W
0V
0U
0T
0S
0R
0Q
0P
0O
0N
0M
0L
0K
0J
0I
1i
1j
03!
02!
01!
00!
0/!
0.!
0-!
0,!
0+!
0*!
0)!
0(!
0'!
0&!
0%!
0$!
0#!
0"!
0!!
0~
0}
0|
0{
0z
0y
0x
0w
0v
0u
0t
0s
0r
0S!
0R!
0Q!
1P!
1O!
0N!
1M!
0L!
0K!
1J!
0I!
0H!
0G!
0F!
0E!
0D!
0C!
0B!
0A!
0@!
0?!
0>!
0=!
0<!
0;!
0:!
09!
08!
07!
06!
05!
04!
1T!
0q
0p
0o
0n
0G
0F
0E
0D
0;
0:
09
08
$end
#5000
1%
18
1D
1n
#10000
0%
08
0D
0n
#15000
1%
18
1D
1n
#20000
0%
08
0D
0n
#25000
1%
18
1D
1n
#30000
0%
08
0D
0n
#35000
1%
18
1D
1n
#40000
0%
08
0D
0n
#45000
1%
18
1D
1n
1&
19
1E
1o
#50000
0%
08
0D
0n
#55000
1%
18
1D
1n
b1 V!
b1 H
b1 =
13!
#60000
0%
08
0D
0n
#65000
1%
18
1D
1n
b10 V!
b10 H
b10 =
03!
12!
#70000
0%
08
0D
0n
#75000
1%
18
1D
1n
b11 V!
b11 H
b11 =
13!
#80000
0%
08
0D
0n
#85000
1%
18
1D
1n
b100 V!
b100 H
b100 =
03!
02!
11!
#90000
0%
08
0D
0n
#95000
1%
18
1D
1n
b101 V!
b101 H
b101 =
13!
#100000
0%
08
0D
0n
#105000
1%
18
1D
1n
b110 V!
b110 H
b110 =
03!
12!
#110000
0%
08
0D
0n
#115000
1%
18
1D
1n
b111 V!
b111 H
b111 =
13!
#120000
0%
08
0D
0n
#125000
1%
18
1D
1n
b1000 V!
b1000 H
b1000 =
03!
02!
01!
10!
#130000
0%
08
0D
0n
#135000
1%
18
1D
1n
b1001 V!
b1001 H
b1001 =
13!
#140000
0%
08
0D
0n
#145000
1%
18
1D
1n
b1010 V!
b1010 H
b1010 =
03!
12!
#150000
0%
08
0D
0n
#155000
1%
18
1D
1n
b1011 V!
b1011 H
b1011 =
13!
#160000
0%
08
0D
0n
#165000
1%
18
1D
1n
b1100 V!
b1100 H
b1100 =
03!
02!
11!
#170000
0%
08
0D
0n
#175000
1%
18
1D
1n
b1101 V!
b1101 H
b1101 =
13!
#180000
0%
08
0D
0n
