01_Módulo_Básico/Circuitos_Digitais_II/Aulas_06e07/count_ascendente_100/Quartus/rtl/structural/count_ascendente_100.v
// ============================================================================
// Arquivo   : count_ascendente_100 (implementação STRUCTURAL)
// Autor     : Manoel Furtado
// Data      : 26/11/2025
// Ferramentas: Compatível com Quartus e Questa (Verilog 2001)
// Descrição : Implementação estrutural do contador módulo 100. O design é
//             composto pela interconexão de blocos menores.
// Revisão   : v1.0 — criação inicial
// ============================================================================

`timescale 1ns/1ps

module count_ascendente_100_struct
#(
    // Parâmetros configuráveis
    parameter integer WIDTH      = 7,  // Largura do contador
    parameter integer MAX_COUNT  = 99  // Módulo do contador
)
(
    // Portas de E/S
    input  wire                     clk,         // Clock
    input  wire                     async_reset, // Reset assíncrono
    output wire [WIDTH-1:0]         count_out    // Saída do contador
);

    // Fios internos para interconexão dos blocos
    wire [WIDTH-1:0] count_reg;         // Saída do registrador (estado atual)
    wire [WIDTH-1:0] incremented_count; // Saída do somador (estado atual + 1)
    wire [WIDTH-1:0] mux_out;           // Saída do multiplexador (próximo estado)
    wire max_reached;                   // Saída do comparador (flag de reset síncrono)

    // Instanciação do Registrador Assíncrono de N bits
    // Armazena o valor atual do contador
    reg_async_nbits
    #(
        .WIDTH(WIDTH)
    ) u_reg_async_nbits (
        .clk        (clk),
        .async_reset(async_reset),
        .d          (mux_out),    // Entrada vem do MUX (próximo estado)
        .q          (count_reg)   // Saída é o estado atual
    );

    // Instanciação do Somador (Incrementador)
    // Calcula o valor atual + 1
    adder_inc_nbits
    #(
        .WIDTH(WIDTH)
    ) u_adder_inc_nbits (
        .a          (count_reg),        // Entrada é o estado atual
        .sum        (incremented_count) // Saída é o valor incrementado
    );

    // Instanciação do Comparador de Igualdade
    // Verifica se o contador atingiu o valor máximo (MAX_COUNT)
    comparator_eq_nbits
    #(
        .WIDTH(WIDTH),
        .CONST_VALUE(MAX_COUNT)
    ) u_comparator_eq_nbits (
        .a          (count_reg),  // Entrada é o estado atual
        .is_equal   (max_reached) // Saída é 1 se igual a MAX_COUNT
    );

    // Instanciação do Multiplexador de 2 canais
    // Seleciona o próximo estado: (atual + 1) ou (0)
    mux2_nbits
    #(
        .WIDTH(WIDTH)
    ) u_mux2_nbits (
        .sel        (max_reached),       // Se max_reached=1, seleciona entrada 'b' (0)
        .a          (incremented_count), // Entrada 'a': valor incrementado
        .b          ({WIDTH{1'b0}}),     // Entrada 'b': valor zero (reset síncrono)
        .y          (mux_out)            // Saída vai para o registrador
    );

    // Conecta o estado interno à saída do módulo
    assign count_out = count_reg;

endmodule

// ============================================================================
// Submódulos Auxiliares
// ============================================================================

// Registrador com Reset Assíncrono
module reg_async_nbits
#(
    parameter integer WIDTH = 7
)
(
    input  wire                 clk,
    input  wire                 async_reset,
    input  wire [WIDTH-1:0]     d,
    output reg  [WIDTH-1:0]     q
);
    // Lógica sequencial padrão
    always @(posedge clk or posedge async_reset) begin
        if (async_reset) begin
            q <= {WIDTH{1'b0}};
        end
        else begin
            q <= d;
        end
    end
endmodule

// Somador (Incrementador de 1)
module adder_inc_nbits
#(
    parameter integer WIDTH = 7
)
(
    input  wire [WIDTH-1:0] a,
    output wire [WIDTH-1:0] sum
);
    // Lógica combinacional de soma
    assign sum = a + 1'b1;
endmodule

// Comparador de Igualdade com Constante
module comparator_eq_nbits
#(
    parameter integer WIDTH       = 7,
    parameter integer CONST_VALUE = 99
)
(
    input  wire [WIDTH-1:0] a,
    output wire             is_equal
);
    // Lógica combinacional de comparação
    assign is_equal = (a == CONST_VALUE[WIDTH-1:0]);
endmodule

// Multiplexador 2 para 1
module mux2_nbits
#(
    parameter integer WIDTH = 7
)
(
    input  wire             sel,
    input  wire [WIDTH-1:0] a,
    input  wire [WIDTH-1:0] b,
    output wire [WIDTH-1:0] y
);
    // Lógica combinacional de seleção
    assign y = sel ? b : a;
endmodule

01_Módulo_Básico/Circuitos_Digitais_II/Aulas_06e07/count_ascendente_100/Quartus/rtl/dataflow/count_ascendente_100.v
// ============================================================================
// Arquivo   : count_ascendente_100 (implementação DATAFLOW)
// Autor     : Manoel Furtado
// Data      : 26/11/2025
// Ferramentas: Compatível com Quartus e Questa (Verilog 2001)
// Descrição : Implementação em estilo "dataflow" usando sinais intermediários
//             para representar o próximo valor do contador. O registrador em
//             si é descrito em um bloco sequencial simples, enquanto a lógica
//             combinacional do próximo estado é feita via assign.
// Revisão   : v1.0 — criação inicial
// ============================================================================

`timescale 1ns/1ps

module count_ascendente_100_data
#(
    // Parâmetros configuráveis
    parameter integer WIDTH      = 7,  // Largura do contador
    parameter integer MAX_COUNT  = 99  // Módulo do contador
)
(
    // Portas
    input  wire                     clk,         // Clock
    input  wire                     async_reset, // Reset assíncrono
    output wire [WIDTH-1:0]         count_out    // Saída (wire pois é atribuída via assign)
);

    // Sinais internos
    reg [WIDTH-1:0] count_reg;       // Registrador que armazena o estado atual
    wire max_reached;                // Sinal de controle: indica se atingiu o máximo
    wire [WIDTH-1:0] next_count;     // Sinal combinacional: próximo valor do contador

    // Lógica Combinacional (Dataflow)
    // 1. Verifica se o valor atual é igual ao máximo
    assign max_reached = (count_reg == MAX_COUNT[WIDTH-1:0]);
    
    // 2. Define o próximo valor usando operador ternário (mux)
    // Se max_reached for verdadeiro, próximo é 0; senão, é atual + 1
    assign next_count  = max_reached ? {WIDTH{1'b0}} :
                                      (count_reg + 1'b1);

    // Lógica Sequencial (Registrador de Estado)
    always @(posedge clk or posedge async_reset) begin
        // Reset assíncrono
        if (async_reset) begin
            count_reg <= {WIDTH{1'b0}}; // Zera o registrador
        end
        // Atualização síncrona
        else begin
            count_reg <= next_count;    // Carrega o próximo valor calculado
        end
    end

    // Atribuição da saída
    assign count_out = count_reg; // Conecta o registrador interno à saída do módulo

endmodule

01_Módulo_Básico/Circuitos_Digitais_II/Aulas_06e07/count_ascendente_100/Questa/rtl/behavioral/count_ascendente_100.v
// ============================================================================
// Arquivo   : count_ascendente_100 (implementação BEHAVIORAL)
// Autor     : Manoel Furtado
// Data      : 26/11/2025
// Ferramentas: Compatível com Quartus e Questa (Verilog 2001)
// Descrição : Contador síncrono ascendente módulo 100, com reset assíncrono
//             ativo em nível alto. A abordagem behavioral descreve o
//             comportamento completo do registrador usando um único bloco
//             always sensível à borda de subida do clock e à borda de subida
//             do sinal de reset. Quando o reset é ativado, a saída vai
//             imediatamente para zero. Quando o contador atinge MAX_COUNT
//             (99 por padrão), ele retorna para zero no próximo pulso de
//             clock, implementando um contador módulo 100. Parametrização de
//             largura permite reutilizar o módulo com outros limites.
// Revisão   : v1.0 — criação inicial
// ============================================================================

`timescale 1ns/1ps

module count_ascendente_100_behav
#(
    // Parâmetros configuráveis para largura do contador e valor máximo de contagem
    parameter integer WIDTH      = 7,  // Largura do barramento de saída (bits)
    parameter integer MAX_COUNT  = 99  // Valor máximo de contagem (módulo)
)
(
    // Declaração das portas de entrada e saída
    input  wire                     clk,         // Sinal de clock (borda de subida)
    input  wire                     async_reset, // Reset assíncrono (ativo em nível alto)
    output reg  [WIDTH-1:0]         count_out    // Saída do contador (tipo reg pois é atribuído em always)
);

    // Bloco always sequencial: sensível à borda de subida do clock ou do reset
    // A lista de sensibilidade inclui 'posedge async_reset' para comportamento assíncrono
    always @(posedge clk or posedge async_reset) begin
        // Verificação prioritária do Reset (Assíncrono)
        if (async_reset) begin
            // Se reset for 1, a saída é forçada a 0 imediatamente, independente do clock
            count_out <= {WIDTH{1'b0}}; // {WIDTH{1'b0}} replica o bit 0 'WIDTH' vezes
        end
        // Lógica Síncrona (na borda do clock)
        // Verifica se o contador atingiu o valor máximo
        else if (count_out == MAX_COUNT[WIDTH-1:0]) begin
            // Se atingiu o máximo, reinicia para 0 no próximo clock
            count_out <= {WIDTH{1'b0}};
        end
        // Caso normal de contagem
        else begin
            // Incrementa o valor atual em 1
            count_out <= count_out + 1'b1;
        end
    end

endmodule

01_Módulo_Básico/Circuitos_Digitais_II/Aulas_06e07/count_ascendente_100/Questa/tb/tb_count_ascendente_100.v
// ============================================================================
// Arquivo   : tb_count_ascendente_100
// Autor     : Manoel Furtado
// Data      : 26/11/2025
// Ferramentas: Compatível com Questa (Verilog 2001)
// Descrição : Testbench que instancia simultaneamente as três implementações.
// Revisão   : v1.1 — correção de declaração (integer k em escopo de módulo)
// ============================================================================

`timescale 1ns/1ps

module tb_count_ascendente_100;

    // Sinais de estímulo (entradas para os DUTs)
    reg clk;
    reg async_reset;

    // Sinais de monitoramento (saídas dos DUTs)
    wire [6:0] count_behav;
    wire [6:0] count_data;
    wire [6:0] count_struct;

    // Variáveis auxiliares para controle do testbench
    integer i;
    integer total_tests;
    integer success_flag;
    integer k;   // usado na tabela didática

    // Gerador de Clock
    // Período = 10ns (Frequência = 100MHz)
    initial begin
        clk = 1'b0;
        forever #5 clk = ~clk; // Inverte o clock a cada 5ns
    end

    // Gerador de Reset
    initial begin
        async_reset = 1'b1; // Inicia com reset ativo
        #20;
        async_reset = 1'b0; // Desativa reset após 20ns
        // O pulso de reset intermediário foi removido para permitir
        // a visualização da contagem completa de 0 a 99 na tabela didática.
    end

    // Instanciação do DUT (Device Under Test) - Implementação Behavioral
    count_ascendente_100_behav
    #(
        .WIDTH(7),
        .MAX_COUNT(99)
    ) u_count_ascendente_100_behav (
        .clk        (clk),
        .async_reset(async_reset),
        .count_out  (count_behav)
    );

    // Instanciação do DUT - Implementação Dataflow
    count_ascendente_100_data
    #(
        .WIDTH(7),
        .MAX_COUNT(99)
    ) u_count_ascendente_100_data (
        .clk        (clk),
        .async_reset(async_reset),
        .count_out  (count_data)
    );

    // Instanciação do DUT - Implementação Structural
    count_ascendente_100_struct
    #(
        .WIDTH(7),
        .MAX_COUNT(99)
    ) u_count_ascendente_100_struct (
        .clk        (clk),
        .async_reset(async_reset),
        .count_out  (count_struct)
    );

    // Configuração para geração de arquivo de onda (VCD)
    initial begin
        $dumpfile("wave.vcd");
        $dumpvars(0, tb_count_ascendente_100);
    end

    // Processo principal de verificação (Self-Checking)
    initial begin
        total_tests  = 0;
        success_flag = 1; // Assume sucesso inicialmente

        // Aguarda o fim do reset inicial e a primeira borda de clock
        @(negedge async_reset);
        @(posedge clk);

        // Loop de teste por 300 ciclos de clock
        for (i = 0; i < 300; i = i + 1) begin
            @(posedge clk); // Sincroniza com a borda de subida
            total_tests = total_tests + 1;

            // Compara as saídas das três implementações
            // Se houver qualquer divergência, reporta erro
            if ((count_behav !== count_data) || (count_data !== count_struct)) begin
                $display("ERRO em %0t ns: behav=%0d data=%0d struct=%0d",
                         $time, count_behav, count_data, count_struct);
                success_flag = 0;
            end
        end

        // Relatório final de verificação
        if (success_flag) begin
            $display("SUCESSO: Todas as implementacoes estao consistentes em %0d testes.",
                     total_tests);
        end
        else begin
            $display("FALHA: Inconsistencias encontradas em %0d testes.",
                     total_tests);
        end

        $display("Fim da simulacao.");
        $finish; // Encerra a simulação
    end

    // Processo separado para gerar a Tabela Didática no console
    initial begin
        // Aguarda o reset inicial
        @(negedge async_reset);
        // Removido o wait extra de clock para pegar o valor 0 inicial
        
        $display("========================================================");
        $display(" TABELA DIDATICA - Contador modulo 100 (implement. BEHAV)");
        $display(" tempo(ns) | count_dec | count_bin");
        $display("--------------------------------------------------------");

        // Imprime os valores de 0 a 99 (e o retorno a 0)
        // Loop aumentado para 105 para mostrar o ciclo completo e o wrap-around
        for (k = 0; k < 105; k = k + 1) begin
            @(posedge clk);
            $display("%9t | %9d | %07b",
                     $time, count_behav, count_behav);
        end

        $display("========================================================");
    end

endmodule

01_Módulo_Básico/Circuitos_Digitais_II/Aulas_06e07/count_ascendente_100/Questa/scripts/wave.vcd
$date
	Wed Nov 26 21:23:31 2025
$end
$version
	Questa Intel Starter FPGA Edition Version 2024.3
$end
$timescale
	1ps
$end

$scope module tb_count_ascendente_100 $end
$var reg 1 ! clk $end
$var reg 1 " async_reset $end
$var wire 1 # count_behav [6] $end
$var wire 1 $ count_behav [5] $end
$var wire 1 % count_behav [4] $end
$var wire 1 & count_behav [3] $end
$var wire 1 ' count_behav [2] $end
$var wire 1 ( count_behav [1] $end
$var wire 1 ) count_behav [0] $end
$var wire 1 * count_data [6] $end
$var wire 1 + count_data [5] $end
$var wire 1 , count_data [4] $end
$var wire 1 - count_data [3] $end
$var wire 1 . count_data [2] $end
$var wire 1 / count_data [1] $end
$var wire 1 0 count_data [0] $end
$var wire 1 1 count_struct [6] $end
$var wire 1 2 count_struct [5] $end
$var wire 1 3 count_struct [4] $end
$var wire 1 4 count_struct [3] $end
$var wire 1 5 count_struct [2] $end
$var wire 1 6 count_struct [1] $end
$var wire 1 7 count_struct [0] $end
$var integer 32 8 i $end
$var integer 32 9 total_tests $end
$var integer 32 : success_flag $end
$var integer 32 ; k $end

$scope module u_count_ascendente_100_behav $end
$var parameter 32 < WIDTH $end
$var parameter 32 = MAX_COUNT $end
$var wire 1 > clk $end
$var wire 1 ? async_reset $end
$var reg 7 @ count_out [6:0] $end
$upscope $end

$scope module u_count_ascendente_100_data $end
$var parameter 32 A WIDTH $end
$var parameter 32 B MAX_COUNT $end
$var wire 1 C clk $end
$var wire 1 D async_reset $end
$var wire 1 * count_out [6] $end
$var wire 1 + count_out [5] $end
$var wire 1 , count_out [4] $end
$var wire 1 - count_out [3] $end
$var wire 1 . count_out [2] $end
$var wire 1 / count_out [1] $end
$var wire 1 0 count_out [0] $end
$var reg 7 E count_reg [6:0] $end
$var wire 1 F max_reached $end
$var wire 1 G next_count [6] $end
$var wire 1 H next_count [5] $end
$var wire 1 I next_count [4] $end
$var wire 1 J next_count [3] $end
$var wire 1 K next_count [2] $end
$var wire 1 L next_count [1] $end
$var wire 1 M next_count [0] $end
$upscope $end

$scope module u_count_ascendente_100_struct $end
$var parameter 32 N WIDTH $end
$var parameter 32 O MAX_COUNT $end
$var wire 1 P clk $end
$var wire 1 Q async_reset $end
$var wire 1 1 count_out [6] $end
$var wire 1 2 count_out [5] $end
$var wire 1 3 count_out [4] $end
$var wire 1 4 count_out [3] $end
$var wire 1 5 count_out [2] $end
$var wire 1 6 count_out [1] $end
$var wire 1 7 count_out [0] $end
$var wire 1 R count_reg [6] $end
$var wire 1 S count_reg [5] $end
$var wire 1 T count_reg [4] $end
$var wire 1 U count_reg [3] $end
$var wire 1 V count_reg [2] $end
$var wire 1 W count_reg [1] $end
$var wire 1 X count_reg [0] $end
$var wire 1 Y incremented_count [6] $end
$var wire 1 Z incremented_count [5] $end
$var wire 1 [ incremented_count [4] $end
$var wire 1 \ incremented_count [3] $end
$var wire 1 ] incremented_count [2] $end
$var wire 1 ^ incremented_count [1] $end
$var wire 1 _ incremented_count [0] $end
$var wire 1 ` mux_out [6] $end
$var wire 1 a mux_out [5] $end
$var wire 1 b mux_out [4] $end
$var wire 1 c mux_out [3] $end
$var wire 1 d mux_out [2] $end
$var wire 1 e mux_out [1] $end
$var wire 1 f mux_out [0] $end
$var wire 1 g max_reached $end

$scope module u_reg_async_nbits $end
$var parameter 32 h WIDTH $end
$var wire 1 P clk $end
$var wire 1 Q async_reset $end
$var wire 1 ` d [6] $end
$var wire 1 a d [5] $end
$var wire 1 b d [4] $end
$var wire 1 c d [3] $end
$var wire 1 d d [2] $end
$var wire 1 e d [1] $end
$var wire 1 f d [0] $end
$var reg 7 i q [6:0] $end
$upscope $end

$scope module u_adder_inc_nbits $end
$var parameter 32 j WIDTH $end
$var wire 1 R a [6] $end
$var wire 1 S a [5] $end
$var wire 1 T a [4] $end
$var wire 1 U a [3] $end
$var wire 1 V a [2] $end
$var wire 1 W a [1] $end
$var wire 1 X a [0] $end
$var wire 1 Y sum [6] $end
$var wire 1 Z sum [5] $end
$var wire 1 [ sum [4] $end
$var wire 1 \ sum [3] $end
$var wire 1 ] sum [2] $end
$var wire 1 ^ sum [1] $end
$var wire 1 _ sum [0] $end
$upscope $end

$scope module u_comparator_eq_nbits $end
$var parameter 32 k WIDTH $end
$var parameter 32 l CONST_VALUE $end
$var wire 1 R a [6] $end
$var wire 1 S a [5] $end
$var wire 1 T a [4] $end
$var wire 1 U a [3] $end
$var wire 1 V a [2] $end
$var wire 1 W a [1] $end
$var wire 1 X a [0] $end
$var wire 1 g is_equal $end
$upscope $end

$scope module u_mux2_nbits $end
$var parameter 32 m WIDTH $end
$var wire 1 g sel $end
$var wire 1 Y a [6] $end
$var wire 1 Z a [5] $end
$var wire 1 [ a [4] $end
$var wire 1 \ a [3] $end
$var wire 1 ] a [2] $end
$var wire 1 ^ a [1] $end
$var wire 1 _ a [0] $end
$var wire 1 n b [6] $end
$var wire 1 o b [5] $end
$var wire 1 p b [4] $end
$var wire 1 q b [3] $end
$var wire 1 r b [2] $end
$var wire 1 s b [1] $end
$var wire 1 t b [0] $end
$var wire 1 ` y [6] $end
$var wire 1 a y [5] $end
$var wire 1 b y [4] $end
$var wire 1 c y [3] $end
$var wire 1 d y [2] $end
$var wire 1 e y [1] $end
$var wire 1 f y [0] $end
$upscope $end
$upscope $end
$upscope $end
$enddefinitions $end
#0
$dumpvars
0!
1"
b0 @
b0 E
b0 i
b111 <
b1100011 =
b111 A
b1100011 B
b111 N
b1100011 O
b111 h
b111 j
b111 k
b1100011 l
b111 m
bx 8
b0 9
b1 :
bx ;
0)
0(
0'
0&
0%
0$
0#
00
0/
0.
0-
0,
0+
0*
07
06
05
04
03
02
01
0F
1M
0L
0K
0J
0I
0H
0G
0X
0W
0V
0U
0T
0S
0R
1_
0^
0]
0\
0[
0Z
0Y
1f
0e
0d
0c
0b
0a
0`
0g
1Q
0P
1D
0C
1?
0>
0t
0s
0r
0q
0p
0o
0n
$end
#5000
1!
1>
1C
1P
#10000
0!
0>
0C
0P
#15000
1!
1>
1C
1P
#20000
0"
0!
0?
0D
0Q
0>
0C
0P
b0 ;
#25000
1!
1>
1C
1P
b0 8
b1 ;
b1 i
b1 E
b1 @
1)
10
0M
1L
1X
0_
1^
17
0f
1e
#30000
0!
0>
0C
0P
#35000
1!
1>
1C
1P
b10 ;
b1 9
b1 8
b10 i
b10 E
b10 @
0)
1(
00
1/
1M
0X
1W
1_
07
16
1f
#40000
0!
0>
0C
0P
#45000
1!
1>
1C
1P
b10 9
b10 8
b11 ;
b11 i
b11 E
b11 @
1)
10
0M
0L
1K
1X
0_
0^
1]
17
0f
0e
1d
#50000
0!
0>
0C
0P
#55000
1!
1>
1C
1P
b100 ;
b11 9
b11 8
b100 i
b100 E
b100 @
0)
0(
1'
00
0/
1.
1M
0X
0W
1V
1_
07
06
15
1f
#60000
0!
0>
0C
0P
#65000
1!
1>
1C
1P
b100 9
b100 8
b101 ;
b101 i
b101 E
b101 @
1)
10
0M
1L
1X
0_
1^
17
0f
1e
#70000
0!
0>
0C
0P
#75000
1!
1>
1C
1P
b110 ;
b101 9
b101 8
b110 i
b110 E
b110 @
0)
1(
00
1/
1M
0X
1W
1_
07
16
1f
#80000
0!
0>
0C
0P
#85000
1!
1>
1C
1P
b110 9
b110 8
b111 ;
b111 i
b111 E
b111 @
1)
10
0M
0L
0K
1J
1X
0_
0^
0]
1\
17
0f
0e
0d
1c
#90000
0!
0>
0C
0P
#95000
1!
1>
1C
1P
b1000 ;
b111 9
b111 8
b1000 i
b1000 E
b1000 @
0)
0(
0'
1&
00
0/
0.
1-
1M
0X
0W
0V
1U
1_
07
06
05
14
1f
#100000
0!
0>
0C
0P
#105000
1!
1>
1C
1P
b1000 9
b1000 8
b1001 ;
b1001 i
b1001 E
b1001 @
1)
10
0M
1L
1X
0_
1^
17
0f
1e
#110000
0!
0>
0C
0P
#115000
1!
1>
1C
1P
b1010 ;
b1001 9
b1001 8
b1010 i
b1010 E
b1010 @
0)
1(
00
1/
1M
0X
1W
1_
07
16
1f
#120000
0!
0>
0C
0P
#125000
1!
1>
1C
1P
b1010 9
b1010 8
b1011 ;
b1011 i
b1011 E
b1011 @
1)
10
0M
0L
1K
1X
0_
0^
1]
17
0f
0e
1d
#130000
0!
0>
0C
0P
#135000
1!
1>
1C
1P
b1100 ;
b1011 9
b1011 8
b1100 i
b1100 E
b1100 @
0)
0(
1'
00
0/
1.
1M
0X
0W
1V
1_
07
06
15
1f
#140000
0!
0>
0C
0P
#145000
1!
1>
1C
1P
b1100 9
b1100 8
b1101 ;
b1101 i
b1101 E
b1101 @
1)
10
0M
1L
1X
0_
1^
17
0f
1e
#150000
0!
0>
0C
0P
#155000
1!
1>
1C
1P
b1110 ;
b1101 9
b1101 8
b1110 i
b1110 E
b1110 @
0)
1(
00
1/
1M
0X
1W
1_
07
16
1f
#160000
0!
0>
0C
0P
#165000
1!
1>
1C
1P
b1110 9
b1110 8
b1111 ;
b1111 i
b1111 E
b1111 @
1)
10
0M
0L
0K
0J
1I
1X
0_
0^
0]
0\
1[
17
0f
0e
0d
0c
1b
#170000
0!
0>
0C
0P
#175000
1!
1>
1C
1P
b10000 ;
b1111 9
b1111 8
b10000 i
b10000 E
b10000 @
0)
0(
0'
0&
1%
00
0/
0.
0-
1,
1M
0X
0W
0V
0U
1T
1_
07
06
05
04
13
1f
#180000
0!
0>
0C
0P
#185000
1!
1>
1C
1P
b10000 9
b10000 8
b10001 ;
b10001 i
b10001 E
b10001 @
1)
10
0M
1L
1X
0_
1^
17
0f
1e
#190000
0!
0>
0C
0P
#195000
1!
1>
1C
1P
b10010 ;
b10001 9
b10001 8
b10010 i
b10010 E
b10010 @
0)
1(
00
1/
1M
0X
1W
1_
07
16
1f
#200000
0!
0>
0C
0P
#205000
1!
1>
1C
1P
b10010 9
b10010 8
b10011 ;
b10011 i
b10011 E
b10011 @
1)
10
0M
0L
1K
1X
0_
0^
1]
17
0f
0e
1d
#210000
0!
0>
0C
0P
#215000
1!
1>
1C
1P
b10100 ;
b10011 9
b10011 8
b10100 i
b10100 E
b10100 @
0)
0(
1'
00
0/
1.
1M
0X
0W
1V
1_
07
06
15
1f
#220000
0!
0>
0C
0P
#225000
1!
1>
1C
1P
b10100 9
b10100 8
b10101 ;
b10101 i
b10101 E
b10101 @
1)
10
0M
1L
1X
0_
1^
17
0f
1e
#230000
0!
0>
0C
0P
#235000
1!
1>
1C
1P
b10110 ;
b10101 9
b10101 8
b10110 i
b10110 E
b10110 @
0)
1(
00
1/
1M
0X
1W
1_
07
16
1f
#240000
0!
0>
0C
0P
#245000
1!
1>
1C
1P
b10110 9
b10110 8
b10111 ;
b10111 i
b10111 E
b10111 @
1)
10
0M
0L
0K
1J
1X
0_
0^
0]
1\
17
0f
0e
0d
1c
#250000
0!
0>
0C
0P
#255000
1!
1>
1C
1P
b11000 ;
b10111 9
b10111 8
b11000 i
b11000 E
b11000 @
0)
0(
0'
1&
00
0/
0.
1-
1M
0X
0W
0V
1U
1_
07
06
05
14
1f
#260000
0!
0>
0C
0P
#265000
1!
1>
1C
1P
b11000 9
b11000 8
b11001 ;
b11001 i
b11001 E
b11001 @
1)
10
0M
1L
1X
0_
1^
17
0f
1e
#270000
0!
0>
0C
0P
#275000
1!
1>
1C
1P
b11010 ;
b11001 9
b11001 8
b11010 i
b11010 E
b11010 @
0)
1(
00
1/
1M
0X
1W
1_
07
16
1f
#280000
0!
0>
0C
0P
#285000
1!
1>
1C
1P
b11010 9
b11010 8
b11011 ;
b11011 i
b11011 E
b11011 @
1)
10
0M
0L
1K
1X
0_
0^
1]
17
0f
0e
1d
#290000
0!
0>
0C
0P
#295000
1!
1>
1C
1P
b11100 ;
b11011 9
b11011 8
b11100 i
b11100 E
b11100 @
0)
0(
1'
00
0/
1.
1M
0X
0W
1V
1_
07
06
15
1f
#300000
0!
0>
0C
0P
#305000
1!
1>
1C
1P
b11100 9
b11100 8
b11101 ;
b11101 i
b11101 E
b11101 @
1)
10
0M
1L
1X
0_
1^
17
0f
1e
#310000
0!
0>
0C
0P
#315000
1!
1>
1C
1P
b11110 ;
b11101 9
b11101 8
b11110 i
b11110 E
b11110 @
0)
1(
00
1/
1M
0X
1W
1_
07
16
1f
#320000
0!
0>
0C
0P
#325000
1!
1>
1C
1P
b11110 9
b11110 8
b11111 ;
b11111 i
b11111 E
b11111 @
1)
10
0M
0L
0K
0J
0I
1H
1X
0_
0^
0]
0\
0[
1Z
17
0f
0e
0d
0c
0b
1a
#330000
0!
0>
0C
0P
#335000
1!
1>
1C
1P
b100000 ;
b11111 9
b11111 8
b100000 i
b100000 E
b100000 @
0)
0(
0'
0&
0%
1$
00
0/
0.
0-
0,
1+
1M
0X
0W
0V
0U
0T
1S
1_
07
06
05
04
03
12
1f
#340000
0!
0>
0C
0P
#345000
1!
1>
1C
1P
b100000 9
b100000 8
b100001 ;
b100001 i
b100001 E
b100001 @
1)
10
0M
1L
1X
0_
1^
17
0f
1e
#350000
0!
0>
0C
0P
#355000
1!
1>
1C
1P
b100010 ;
b100001 9
b100001 8
b100010 i
b100010 E
b100010 @
0)
1(
00
1/
1M
0X
1W
1_
07
16
1f
#360000
0!
0>
0C
0P
#365000
1!
1>
1C
1P
b100010 9
b100010 8
b100011 ;
b100011 i
b100011 E
b100011 @
1)
10
0M
0L
1K
1X
0_
0^
1]
17
0f
0e
1d
#370000
0!
0>
0C
0P
#375000
1!
1>
1C
1P
b100100 ;
b100011 9
b100011 8
b100100 i
b100100 E
b100100 @
0)
0(
1'
00
0/
1.
1M
0X
0W
1V
1_
07
06
15
1f
#380000
0!
0>
0C
0P
#385000
1!
1>
1C
1P
b100100 9
b100100 8
b100101 ;
b100101 i
b100101 E
b100101 @
1)
10
0M
1L
1X
0_
1^
17
0f
1e
#390000
0!
0>
0C
0P
#395000
1!
1>
1C
1P
b100110 ;
b100101 9
b100101 8
b100110 i
b100110 E
b100110 @
0)
1(
00
1/
1M
0X
1W
1_
07
16
1f
#400000
0!
0>
0C
0P
#405000
1!
1>
1C
1P
b100110 9
b100110 8
b100111 ;
b100111 i
b100111 E
b100111 @
1)
10
0M
0L
0K
1J
1X
0_
0^
0]
1\
17
0f
0e
0d
1c
#410000
0!
0>
0C
0P
#415000
1!
1>
1C
1P
b101000 ;
b100111 9
b100111 8
b101000 i
b101000 E
b101000 @
0)
0(
0'
1&
00
0/
0.
1-
1M
0X
0W
0V
1U
1_
07
06
05
14
1f
#420000
0!
0>
0C
0P
#425000
1!
1>
1C
1P
b101000 9
b101000 8
b101001 ;
b101001 i
b101001 E
b101001 @
1)
10
0M
1L
1X
0_
1^
17
0f
1e
#430000
0!
0>
0C
0P
#435000
1!
1>
1C
1P
b101010 ;
b101001 9
b101001 8
b101010 i
b101010 E
b101010 @
0)
1(
00
1/
1M
0X
1W
1_
07
16
1f
#440000
0!
0>
0C
0P
#445000
1!
1>
1C
1P
b101010 9
b101010 8
b101011 ;
b101011 i
b101011 E
b101011 @
1)
10
0M
0L
1K
1X
0_
0^
1]
17
0f
0e
1d
#450000
0!
0>
0C
0P
#455000
1!
1>
1C
1P
b101100 ;
b101011 9
b101011 8
b101100 i
b101100 E
b101100 @
0)
0(
1'
00
0/
1.
1M
0X
0W
1V
1_
07
06
15
1f
#460000
0!
0>
0C
0P
#465000
1!
1>
1C
1P
b101100 9
b101100 8
b101101 ;
b101101 i
b101101 E
b101101 @
1)
10
0M
1L
1X
0_
1^
17
0f
1e
#470000
0!
0>
0C
0P
#475000
1!
1>
1C
1P
b101110 ;
b101101 9
b101101 8
b101110 i
b101110 E
b101110 @
0)
1(
00
1/
1M
0X
1W
1_
07
16
1f
#480000
0!
0>
0C
0P
#485000
1!
1>
1C
1P
b101110 9
b101110 8
b101111 ;
b101111 i
b101111 E
b101111 @
1)
10
0M
0L
0K
0J
1I
1X
0_
0^
0]
0\
1[
17
0f
0e
0d
0c
1b
#490000
0!
0>
0C
0P
#495000
1!
1>
1C
1P
b110000 ;
b101111 9
b101111 8
b110000 i
b110000 E
b110000 @
0)
0(
0'
0&
1%
00
0/
0.
0-
1,
1M
0X
0W
0V
0U
1T
1_
07
06
05
04
13
1f
#500000
0!
0>
0C
0P
#505000
1!
1>
1C
1P
b110000 9
b110000 8
b110001 ;
b110001 i
b110001 E
b110001 @
1)
10
0M
1L
1X
0_
1^
17
0f
1e
#510000
0!
0>
0C
0P
#515000
1!
1>
1C
1P
b110010 ;
b110001 9
b110001 8
b110010 i
b110010 E
b110010 @
0)
1(
00
1/
1M
0X
1W
1_
07
16
1f
#520000
0!
0>
0C
0P
#525000
1!
1>
1C
1P
b110010 9
b110010 8
b110011 ;
b110011 i
b110011 E
b110011 @
1)
10
0M
0L
1K
1X
0_
0^
1]
17
0f
0e
1d
#530000
0!
0>
0C
0P
#535000
1!
1>
1C
1P
b110100 ;
b110011 9
b110011 8
b110100 i
b110100 E
b110100 @
0)
0(
1'
00
0/
1.
1M
0X
0W
1V
1_
07
06
15
1f
#540000
0!
0>
0C
0P
#545000
1!
1>
1C
1P
b110100 9
b110100 8
b110101 ;
b110101 i
b110101 E
b110101 @
1)
10
0M
1L
1X
0_
1^
17
0f
1e
#550000
0!
0>
0C
0P
#555000
1!
1>
1C
1P
b110110 ;
b110101 9
b110101 8
b110110 i
b110110 E
b110110 @
0)
1(
00
1/
1M
0X
1W
1_
07
16
1f
#560000
0!
0>
0C
0P
#565000
1!
1>
1C
1P
b110110 9
b110110 8
b110111 ;
b110111 i
b110111 E
b110111 @
1)
10
0M
0L
0K
1J
1X
0_
0^
0]
1\
17
0f
0e
0d
1c
#570000
0!
0>
0C
0P
#575000
1!
1>
1C
1P
b111000 ;
b110111 9
b110111 8
b111000 i
b111000 E
b111000 @
0)
0(
0'
1&
00
0/
0.
1-
1M
0X
0W
0V
1U
1_
07
06
05
14
1f
#580000
0!
0>
0C
0P
#585000
1!
1>
1C
1P
b111000 9
b111000 8
b111001 ;
b111001 i
b111001 E
b111001 @
1)
10
0M
1L
1X
0_
1^
17
0f
1e
