01_Módulo_Básico/Circuitos_Digitais_II/Aulas_06e07/count_sync_pwm_2/Quartus/rtl/behavioral/seven_seg_driver.v

`timescale 1ns/1ps

// ============================================================================
// Módulo: seven_seg_driver
// Descrição: Controlador para display de 7 segmentos multiplexado.
//            Exibe o valor do duty cycle (25, 50, 75, 100) com base na seleção.
//            Controla os segmentos (a-g) e os anodos para varredura.
// ============================================================================

module seven_seg_driver #(
    // Frequência do clock do sistema em Hz (padrão 100 MHz)
    parameter CLK_FREQ = 100_000_000
) (
    input wire clk,            // Clock do sistema
    input wire reset_n,        // Reset assíncrono ativo em nível baixo
    input wire [1:0] duty_sel, // Seleção do duty cycle: 00=25%, 01=50%, 10=75%, 11=100%
    output reg [6:0] segments, // Saída para os segmentos (a,b,c,d,e,f,g) - Ativo em 0
    output reg [3:0] anodes    // Saída para os anodos (controle dos dígitos) - Ativo em 0
);

    // Registradores para armazenar o valor numérico de cada um dos 4 dígitos
    reg [3:0] digit0; // Dígito da direita (unidades)
    reg [3:0] digit1; // Dígito das dezenas
    reg [3:0] digit2; // Dígito das centenas
    reg [3:0] digit3; // Dígito da esquerda (milhares) - não usado aqui
    
    // --- Decodificação da Seleção de Duty Cycle ---
    // Define quais números devem aparecer nos dígitos com base em duty_sel.
    // Usamos o valor 15 (4'd15) para representar "apagado" (Blank).
    always @* begin
        case (duty_sel)
            2'b00: begin // Caso 25%
                digit3 = 4'd15; // Apagado
                digit2 = 4'd15; // Apagado
                digit1 = 4'd2;  // Exibe '2'
                digit0 = 4'd5;  // Exibe '5' -> Resultado "25"
            end
            2'b01: begin // Caso 50%
                digit3 = 4'd15; // Apagado
                digit2 = 4'd15; // Apagado
                digit1 = 4'd5;  // Exibe '5'
                digit0 = 4'd0;  // Exibe '0' -> Resultado "50"
            end
            2'b10: begin // Caso 75%
                digit3 = 4'd15; // Apagado
                digit2 = 4'd15; // Apagado
                digit1 = 4'd7;  // Exibe '7'
                digit0 = 4'd5;  // Exibe '5' -> Resultado "75"
            end
            2'b11: begin // Caso 100%
                digit3 = 4'd15; // Apagado
                digit2 = 4'd1;  // Exibe '1'
                digit1 = 4'd0;  // Exibe '0'
                digit0 = 4'd0;  // Exibe '0' -> Resultado "100"
            end
            default: begin // Caso padrão de segurança
                digit3 = 4'd15;
                digit2 = 4'd15;
                digit1 = 4'd0;
                digit0 = 4'd0;
            end
        endcase
    end

    // --- Lógica de Multiplexação (Varredura) ---
    // Para controlar 4 dígitos com apenas um conjunto de fios de segmentos,
    // ligamos um dígito de cada vez muito rapidamente.
    
    // Define a contagem para a taxa de atualização.
    // 400 Hz é uma taxa confortável para evitar cintilação (flicker).
    localparam REFRESH_COUNT = CLK_FREQ / 400; 
    
    integer refresh_counter; // Contador para dividir o clock
    reg [1:0] digit_sel;     // Seleciona qual dígito está ativo (0 a 3)

    // Bloco sequencial para o contador de varredura
    always @(posedge clk or negedge reset_n) begin
        if (!reset_n) begin
            refresh_counter <= 0;
            digit_sel <= 0;
        end else begin
            // Se atingiu a contagem para trocar de dígito...
            if (refresh_counter >= REFRESH_COUNT) begin
                refresh_counter <= 0;       // Reseta contador
                digit_sel <= digit_sel + 1; // Passa para o próximo dígito
            end else begin
                refresh_counter <= refresh_counter + 1; // Incrementa contador
            end
        end
    end

    // Registrador temporário para guardar o valor do dígito ativo no momento
    reg [3:0] current_digit_val;

    // --- Controle dos Anodos e Seleção do Valor ---
    // Ativa o anodo correspondente ao digit_sel e seleciona o valor a ser exibido.
    // Assumindo display Anodo Comum, onde 0 no anodo liga o dígito.
    always @* begin
        case (digit_sel)
            2'b00: begin
                anodes = 4'b1110;          // Liga o dígito 0 (direita)
                current_digit_val = digit0; // Seleciona valor do dígito 0
            end
            2'b01: begin
                anodes = 4'b1101;          // Liga o dígito 1
                current_digit_val = digit1; // Seleciona valor do dígito 1
            end
            2'b10: begin
                anodes = 4'b1011;          // Liga o dígito 2
                current_digit_val = digit2; // Seleciona valor do dígito 2
            end
            2'b11: begin
                anodes = 4'b0111;          // Liga o dígito 3 (esquerda)
                current_digit_val = digit3; // Seleciona valor do dígito 3
            end
        endcase
    end

    // --- Decodificador de 7 Segmentos ---
    // Converte o valor numérico (0-9) para os segmentos (a-g).
    // Padrão: Segmentos ativos em nível BAIXO (0 liga o LED).
    // Mapeamento: gfedcba
    always @* begin
        case (current_digit_val)
            4'd0: segments = 7'b1000000; // 0: acende a,b,c,d,e,f
            4'd1: segments = 7'b1111001; // 1: acende b,c
            4'd2: segments = 7'b0100100; // 2: acende a,b,d,e,g
            4'd3: segments = 7'b0110000; // 3: acende a,b,c,d,g
            4'd4: segments = 7'b0011001; // 4: acende b,c,f,g
            4'd5: segments = 7'b0010010; // 5: acende a,c,d,f,g
            4'd6: segments = 7'b0000010; // 6: acende a,c,d,e,f,g
            4'd7: segments = 7'b1111000; // 7: acende a,b,c
            4'd8: segments = 7'b0000000; // 8: acende todos
            4'd9: segments = 7'b0010000; // 9: acende a,b,c,d,f,g
            4'd15: segments = 7'b1111111; // Blank: apaga tudo (1111111)
            default: segments = 7'b1111111; // Padrão: apagado
        endcase
    end

endmodule

01_Módulo_Básico/Circuitos_Digitais_II/Aulas_06e07/count_sync_pwm_2/Questa/rtl/behavioral/pwm_50hz_behav.v

// ============================================================================
// Arquivo  : pwm_50hz_behav.v (Implementação Behavioral)
// Autor    : Manoel Furtado
// Data     : 27/11/2025
// Ferramentas: Compatível com Quartus e Questa (Verilog 2001)
// Descrição: Módulo de geração de PWM a 50 Hz com seleção de duty cycle via
//            entrada de 2 bits. Implementação em estilo behavioral, utilizando
//            um contador síncrono e lógica sequencial dentro de um único bloco
//            always sensível à borda de subida do clock.
// ============================================================================

`timescale 1ns/1ps

module pwm_50hz_behav
#(
    // Parâmetro: Frequência do clock de entrada em Hz (padrão 100 MHz)
    parameter integer CLK_FREQ_HZ = 100_000_000,
    // Parâmetro: Frequência desejada do PWM em Hz (padrão 50 Hz)
    parameter integer PWM_FREQ_HZ = 50,
    // Parâmetro calculado: Número total de ciclos de clock em um período PWM.
    // Ex: 100.000.000 / 50 = 2.000.000 ciclos.
    parameter integer COUNTER_MAX = CLK_FREQ_HZ / PWM_FREQ_HZ
)
(
    input  wire        clk,       // Sinal de clock de 100 MHz
    input  wire        reset_n,   // Reset assíncrono ativo em nível baixo (0 reinicia)
    input  wire [1:0]  duty_sel,  // Seleção de duty cycle: 00=25%, 01=50%, 10=75%, 11=100%
    output reg         pwm_out    // Saída do sinal PWM gerado
);

    // --- Definição dos Limites de Comparação (Thresholds) ---
    // Calculamos os valores do contador onde o sinal deve mudar de nível
    // para atingir a porcentagem desejada.
    
    // Limite para 25% do período: (2.000.000 * 25) / 100 = 500.000
    localparam integer DUTY_25  = (COUNTER_MAX * 25) / 100;
    
    // Limite para 50% do período: (2.000.000 * 50) / 100 = 1.000.000
    localparam integer DUTY_50  = (COUNTER_MAX * 50) / 100;
    
    // Limite para 75% do período: (2.000.000 * 75) / 100 = 1.500.000
    localparam integer DUTY_75  = (COUNTER_MAX * 75) / 100;
    
    // Limite para 100% do período: Igual ao máximo (sinal sempre alto)
    localparam integer DUTY_100 = COUNTER_MAX;

    // --- Contador Principal ---
    // Registrador de 21 bits é suficiente para contar até 2.000.000 (2^21 = 2.097.152)
    reg [20:0] counter;

    // --- Lógica Sequencial do Contador ---
    // Bloco always sensível à borda de subida do clock ou borda de descida do reset
    always @(posedge clk or negedge reset_n) begin
        // Verifica se o reset está ativo (nível baixo)
        if (!reset_n) begin
            // Reinicia o contador para 0
            counter <= 21'd0;
        end else begin
            // Se o contador atingiu o valor máximo do período (menos 1, pois começa em 0)
            if (counter >= (COUNTER_MAX - 1)) begin
                // Reinicia o ciclo do PWM
                counter <= 21'd0;
            end else begin
                // Incrementa o contador em cada ciclo de clock
                counter <= counter + 21'd1;
            end
        end
    end

    // --- Lógica Combinacional de Saída (Comparador) ---
    // Define o valor da saída pwm_out com base no valor atual do contador
    // e na seleção de duty cycle (duty_sel).
    always @* begin
        case (duty_sel)
            2'b00: begin
                // Caso 25%: Saída ALTA se contador < DUTY_25, senão BAIXA
                pwm_out = (counter < DUTY_25) ? 1'b1 : 1'b0;
            end
            2'b01: begin
                // Caso 50%: Saída ALTA se contador < DUTY_50, senão BAIXA
                pwm_out = (counter < DUTY_50) ? 1'b1 : 1'b0;
            end
            2'b10: begin
                // Caso 75%: Saída ALTA se contador < DUTY_75, senão BAIXA
                pwm_out = (counter < DUTY_75) ? 1'b1 : 1'b0;
            end
            2'b11: begin
                // Caso 100%: Saída sempre ALTA
                pwm_out = 1'b1;
            end
            default: begin
                // Caso padrão (segurança): Saída BAIXA
                pwm_out = 1'b0;
            end
        endcase
    end

endmodule

01_Módulo_Básico/Circuitos_Digitais_II/Aulas_06e07/count_sync_pwm_2/Quartus/rtl/behavioral/debounce.v

`timescale 1ns/1ps

// ============================================================================
// Módulo: debounce
// Descrição: Implementa um circuito de debounce para botões mecânicos.
//            O debounce remove oscilações indesejadas (bouncing) que ocorrem
//            quando um botão é pressionado ou solto, garantindo um sinal limpo.
// ============================================================================

module debounce #(
    // Frequência do clock do sistema em Hz (padrão 100 MHz)
    parameter CLK_FREQ = 100_000_000,
    // Tempo de debounce desejado em milissegundos (padrão 10 ms)
    parameter DEBOUNCE_MS = 10
) (
    input wire clk,        // Clock do sistema
    input wire reset_n,    // Reset assíncrono ativo em nível baixo (0 = reset)
    input wire button_in,  // Sinal bruto vindo do botão físico (sujeito a ruído)
    output reg button_out  // Sinal limpo e estável do botão
);

    // Calcula o número máximo de ciclos de clock para atingir o tempo de debounce.
    // Fórmula: (Frequência / 1000) * Tempo_em_ms
    localparam COUNTER_MAX = (CLK_FREQ / 1000) * DEBOUNCE_MS;

    // Contador para medir o tempo de estabilidade do sinal
    integer counter;

    // Registradores para sincronização do sinal de entrada com o clock do sistema
    // Isso evita metaestabilidade.
    reg button_sync_0; // Primeiro estágio de sincronização
    reg button_sync_1; // Segundo estágio de sincronização (sinal sincronizado)

    // Bloco sequencial sensível à borda de subida do clock ou borda de descida do reset
    always @(posedge clk or negedge reset_n) begin
        // Verifica se o reset está ativo (nível baixo)
        if (!reset_n) begin
            // Reseta todos os registradores e o contador
            counter <= 0;
            button_out <= 0;
            button_sync_0 <= 0;
            button_sync_1 <= 0;
        end else begin
            // --- Sincronização ---
            // Captura o sinal de entrada no primeiro flip-flop
            button_sync_0 <= button_in;
            // Passa para o segundo flip-flop para completar a sincronização
            button_sync_1 <= button_sync_0;

            // --- Lógica de Debounce ---
            // Verifica se o sinal sincronizado (button_sync_1) é diferente da saída atual.
            // Se for diferente, significa que houve uma mudança de estado no botão.
            if (button_sync_1 != button_out) begin
                // Se o contador ainda não atingiu o tempo máximo de debounce...
                if (counter < COUNTER_MAX) begin
                    // Incrementa o contador. Estamos esperando o sinal estabilizar.
                    counter <= counter + 1;
                end else begin
                    // Se o contador atingiu o máximo, significa que o sinal ficou estável
                    // pelo tempo determinado (DEBOUNCE_MS).
                    // Atualiza a saída com o novo valor do botão.
                    button_out <= button_sync_1;
                    // Reseta o contador para a próxima detecção.
                    counter <= 0;
                end
            end else begin
                // Se o sinal sincronizado for igual à saída atual (não houve mudança ou
                // a mudança foi ruído passageiro que não durou o tempo suficiente),
                // zera o contador.
                counter <= 0;
            end
        end
    end

endmodule

01_Módulo_Básico/Circuitos_Digitais_II/Aulas_06e07/count_sync_pwm_2/Questa/rtl/behavioral/top_pwm_challenge.v

`timescale 1ns/1ps

// ============================================================================
// Módulo: top_pwm_challenge
// Descrição: Módulo topo de hierarquia para o desafio extra.
//            Integra o gerador de PWM, o controlador de display e a leitura
//            de botões.
// Funcionalidades:
//   - Leitura de botão com debounce para alterar o duty cycle.
//   - Geração de dois canais PWM sincronizados.
//   - Exibição do valor do duty cycle (25, 50, 75, 100) no display de 7 seg.
// ============================================================================

module top_pwm_challenge #(
    // Frequência do clock de entrada (padrão 100 MHz)
    parameter CLK_FREQ_HZ = 100_000_000,
    // Frequência desejada para o sinal PWM (padrão 50 Hz)
    parameter PWM_FREQ_HZ = 50
) (
    input wire clk,            // Clock do sistema
    input wire reset_n,        // Reset assíncrono ativo em nível baixo
    input wire btn_adjust,     // Botão físico para ajuste do duty cycle
    output wire pwm_out_1,     // Saída PWM Canal 1
    output wire pwm_out_2,     // Saída PWM Canal 2
    output wire [6:0] segments,// Saída para segmentos do display
    output wire [3:0] anodes   // Saída para anodos do display
);

    // --- Sinais Internos ---
    wire btn_debounced; // Sinal do botão após passar pelo debounce
    reg btn_prev;       // Registrador para armazenar o estado anterior do botão (detecção de borda)
    reg [1:0] duty_sel; // Registrador de seleção do duty cycle (00..11)

    // --- Instância do Módulo de Debounce ---
    // Filtra o ruído do botão 'btn_adjust' gerando 'btn_debounced'.
    debounce #(
        .CLK_FREQ(CLK_FREQ_HZ),
        .DEBOUNCE_MS(10) // Configura 10ms de tempo de debounce
    ) u_debounce (
        .clk(clk),
        .reset_n(reset_n),
        .button_in(btn_adjust),
        .button_out(btn_debounced)
    );

    // --- Máquina de Estados para Seleção do Duty Cycle ---
    // Detecta a borda de subida do botão debounced e incrementa a seleção.
    always @(posedge clk or negedge reset_n) begin
        if (!reset_n) begin
            duty_sel <= 2'b00; // Inicializa com 25% (00)
            btn_prev <= 1'b0;  // Inicializa estado anterior do botão
        end else begin
            // Atualiza o estado anterior para o próximo ciclo
            btn_prev <= btn_debounced;
            
            // Detecção de borda de subida:
            // Se o botão está ALTO agora (btn_debounced) E estava BAIXO antes (!btn_prev)
            if (btn_debounced && !btn_prev) begin
                // Incrementa a seleção ciclicamente (00 -> 01 -> 10 -> 11 -> 00...)
                duty_sel <= duty_sel + 1'b1;
            end
        end
    end

    // --- Canal PWM 1 ---
    // Instância do gerador PWM behavioral.
    pwm_50hz_behav #(
        .CLK_FREQ_HZ(CLK_FREQ_HZ),
        .PWM_FREQ_HZ(PWM_FREQ_HZ)
    ) u_pwm_ch1 (
        .clk(clk),
        .reset_n(reset_n),
        .duty_sel(duty_sel), // Recebe a seleção controlada pelo botão
        .pwm_out(pwm_out_1)
    );

    // --- Canal PWM 2 ---
    // Segunda instância do gerador PWM, operando simultaneamente.
    // Como recebem o mesmo clock e reset, estarão sincronizados.
    pwm_50hz_behav #(
        .CLK_FREQ_HZ(CLK_FREQ_HZ),
        .PWM_FREQ_HZ(PWM_FREQ_HZ)
    ) u_pwm_ch2 (
        .clk(clk),
        .reset_n(reset_n),
        .duty_sel(duty_sel), // Recebe a mesma seleção
        .pwm_out(pwm_out_2)
    );

    // --- Driver do Display de 7 Segmentos ---
    // Controla a exibição visual do valor do duty cycle.
    seven_seg_driver #(
        .CLK_FREQ(CLK_FREQ_HZ)
    ) u_display (
        .clk(clk),
        .reset_n(reset_n),
        .duty_sel(duty_sel), // Informa qual valor deve ser exibido
        .segments(segments),
        .anodes(anodes)
    );

endmodule

01_Módulo_Básico/Circuitos_Digitais_II/Aulas_06e07/count_sync_pwm_2/Questa/tb/tb_top_pwm_challenge.v

`timescale 1ns/1ps

// ============================================================================
// Módulo: tb_top_pwm_challenge
// Descrição: Testbench para verificar o funcionamento do desafio extra.
//            Simula o pressionamento do botão e observa as saídas PWM e do display.
// ============================================================================

module tb_top_pwm_challenge;

    // --- Parâmetros de Simulação ---
    // Frequência de clock "real" do sistema
    localparam CLK_FREQ_HZ = 100_000_000;
    // Frequência desejada do PWM
    localparam PWM_FREQ_HZ = 50;
    // Período do clock em nanosegundos (10ns para 100MHz)
    localparam CLK_PERIOD_NS = 10.0;

    // --- Sinais do Testbench ---
    reg clk;            // Clock gerado pelo TB
    reg reset_n;        // Reset controlado pelo TB
    reg btn_adjust;     // Botão simulado
    wire pwm_out_1;     // Saída monitorada do Canal 1
    wire pwm_out_2;     // Saída monitorada do Canal 2
    wire [6:0] segments;// Saída monitorada dos segmentos
    wire [3:0] anodes;  // Saída monitorada dos anodos

    // --- Instanciação do DUT (Device Under Test) ---
    // Instanciamos o módulo principal do desafio.
    // NOTA: Reduzimos CLK_FREQ_HZ para 100 kHz APENAS PARA SIMULAÇÃO.
    // Isso faz com que os contadores internos (debounce e PWM) sejam menores,
    // permitindo simular vários ciclos de PWM e eventos de botão em menos tempo.
    // Se usássemos 100 MHz, a simulação demoraria muito para processar 10ms de debounce.
    top_pwm_challenge #(
        .CLK_FREQ_HZ(100_000), // Clock reduzido para acelerar simulação (100 kHz)
        .PWM_FREQ_HZ(50)       // Mantém 50 Hz alvo
    ) u_top (
        .clk(clk),
        .reset_n(reset_n),
        .btn_adjust(btn_adjust),
        .pwm_out_1(pwm_out_1),
        .pwm_out_2(pwm_out_2),
        .segments(segments),
        .anodes(anodes)
    );

    // --- Geração de Clock ---
    // Gera um clock perpétuo com período definido.
    initial begin
        clk = 0;
        // Inverte o clock a cada metade do período
        forever #(CLK_PERIOD_NS/2) clk = ~clk;
    end

    // --- Procedimento de Teste ---
    initial begin
        // Configura arquivo de saída para visualização de ondas (GTKWave/ModelSim)
        $dumpfile("wave_challenge.vcd");
        $dumpvars(0, tb_top_pwm_challenge);

        // --- Inicialização ---
        reset_n = 0;    // Mantém em reset
        btn_adjust = 0; // Botão solto
        
        // Aguarda 10 ciclos de clock
        repeat(10) @(posedge clk);
        reset_n = 1;    // Libera o reset
        
        $display("Iniciando Simulacao...");
        
        // --- Estado Inicial (Duty 25%) ---
        // Aguarda um tempo para estabilização e observação inicial
        repeat(5000) @(posedge clk); 
        
        // --- Teste 1: Mudar para 50% ---
        $display("Pressionando Botao (Mudar para 50%)...");
        btn_adjust = 1; // Pressiona botão
        // Mantém pressionado por tempo suficiente para vencer o debounce.
        // Com clock de 100kHz, 10ms seriam 1000 ciclos.
        // Seguramos por 2000 ciclos para garantir.
        repeat(2000) @(posedge clk); 
        btn_adjust = 0; // Solta botão
        // Aguarda para observar o novo duty cycle
        repeat(5000) @(posedge clk);
        
        // --- Teste 2: Mudar para 75% ---
        $display("Pressionando Botao (Mudar para 75%)...");
        btn_adjust = 1;
        repeat(2000) @(posedge clk);
        btn_adjust = 0;
        repeat(5000) @(posedge clk);

        // --- Teste 3: Mudar para 100% ---
        $display("Pressionando Botao (Mudar para 100%)...");
        btn_adjust = 1;
        repeat(2000) @(posedge clk);
        btn_adjust = 0;
        repeat(5000) @(posedge clk);

        // --- Teste 4: Ciclar de volta para 25% ---
        $display("Pressionando Botao (Voltar para 25%)...");
        btn_adjust = 1;
        repeat(2000) @(posedge clk);
        btn_adjust = 0;
        repeat(5000) @(posedge clk);
        
        $display("Simulacao Finalizada.");
        $finish; // Encerra a simulação
    end

endmodule

01_Módulo_Básico/Circuitos_Digitais_II/Aulas_06e07/count_sync_pwm_2/Questa/scripts/wave_challenge.vcd
$date
	Thu Nov 27 21:24:46 2025
$end
$version
	Questa Intel Starter FPGA Edition Version 2024.3
$end
$timescale
	1ps
$end

$scope module tb_top_pwm_challenge $end
$var parameter 32 ! CLK_FREQ_HZ $end
$var parameter 32 " PWM_FREQ_HZ $end
$var parameter 0 # CLK_PERIOD_NS $end
$var reg 1 $ clk $end
$var reg 1 % reset_n $end
$var reg 1 & btn_adjust $end
$var wire 1 ' pwm_out_1 $end
$var wire 1 ( pwm_out_2 $end
$var wire 1 ) segments [6] $end
$var wire 1 * segments [5] $end
$var wire 1 + segments [4] $end
$var wire 1 , segments [3] $end
$var wire 1 - segments [2] $end
$var wire 1 . segments [1] $end
$var wire 1 / segments [0] $end
$var wire 1 0 anodes [3] $end
$var wire 1 1 anodes [2] $end
$var wire 1 2 anodes [1] $end
$var wire 1 3 anodes [0] $end

$scope module u_top $end
$var parameter 32 4 CLK_FREQ_HZ $end
$var parameter 32 5 PWM_FREQ_HZ $end
$var wire 1 6 clk $end
$var wire 1 7 reset_n $end
$var wire 1 8 btn_adjust $end
$var wire 1 ' pwm_out_1 $end
$var wire 1 ( pwm_out_2 $end
$var wire 1 ) segments [6] $end
$var wire 1 * segments [5] $end
$var wire 1 + segments [4] $end
$var wire 1 , segments [3] $end
$var wire 1 - segments [2] $end
$var wire 1 . segments [1] $end
$var wire 1 / segments [0] $end
$var wire 1 0 anodes [3] $end
$var wire 1 1 anodes [2] $end
$var wire 1 2 anodes [1] $end
$var wire 1 3 anodes [0] $end
$var wire 1 9 btn_debounced $end
$var reg 1 : btn_prev $end
$var reg 2 ; duty_sel [1:0] $end

$scope module u_debounce $end
$var parameter 32 < CLK_FREQ $end
$var parameter 32 = DEBOUNCE_MS $end
$var parameter 32 > COUNTER_MAX $end
$var wire 1 6 clk $end
$var wire 1 7 reset_n $end
$var wire 1 8 button_in $end
$var reg 1 ? button_out $end
$var integer 32 @ counter $end
$var reg 1 A button_sync_0 $end
$var reg 1 B button_sync_1 $end
$upscope $end

$scope module u_pwm_ch1 $end
$var parameter 32 C CLK_FREQ_HZ $end
$var parameter 32 D PWM_FREQ_HZ $end
$var parameter 32 E COUNTER_MAX $end
$var parameter 32 F DUTY_25 $end
$var parameter 32 G DUTY_50 $end
$var parameter 32 H DUTY_75 $end
$var parameter 32 I DUTY_100 $end
$var wire 1 6 clk $end
$var wire 1 7 reset_n $end
$var wire 1 J duty_sel [1] $end
$var wire 1 K duty_sel [0] $end
$var reg 1 L pwm_out $end
$var reg 21 M counter [20:0] $end
$upscope $end

$scope module u_pwm_ch2 $end
$var parameter 32 N CLK_FREQ_HZ $end
$var parameter 32 O PWM_FREQ_HZ $end
$var parameter 32 P COUNTER_MAX $end
$var parameter 32 Q DUTY_25 $end
$var parameter 32 R DUTY_50 $end
$var parameter 32 S DUTY_75 $end
$var parameter 32 T DUTY_100 $end
$var wire 1 6 clk $end
$var wire 1 7 reset_n $end
$var wire 1 U duty_sel [1] $end
$var wire 1 V duty_sel [0] $end
$var reg 1 W pwm_out $end
$var reg 21 X counter [20:0] $end
$upscope $end

$scope module u_display $end
$var parameter 32 Y CLK_FREQ $end
$var parameter 32 Z REFRESH_COUNT $end
$var wire 1 6 clk $end
$var wire 1 7 reset_n $end
$var wire 1 [ duty_sel [1] $end
$var wire 1 \ duty_sel [0] $end
$var reg 7 ] segments [6:0] $end
$var reg 4 ^ anodes [3:0] $end
$var reg 4 _ digit0 [3:0] $end
$var reg 4 ` digit1 [3:0] $end
$var reg 4 a digit2 [3:0] $end
$var reg 4 b digit3 [3:0] $end
$var integer 32 c refresh_counter $end
$var reg 2 d digit_sel [1:0] $end
$var reg 4 e current_digit_val [3:0] $end
$upscope $end
$upscope $end
$upscope $end
$enddefinitions $end
#0
$dumpvars
0$
0%
0&
0:
b0 ;
0?
0A
0B
1L
b0 M
1W
b0 X
b10010 ]
b1110 ^
b101 _
b10 `
b1111 a
b1111 b
b0 d
b101 e
b101111101011110000100000000 !
b110010 "
b11000011010100000 4
b110010 5
b11000011010100000 <
b1010 =
b1111101000 >
b11000011010100000 C
b110010 D
b11111010000 E
b111110100 F
b1111101000 G
b10111011100 H
b11111010000 I
b11000011010100000 N
b110010 O
b11111010000 P
b111110100 Q
b1111101000 R
b10111011100 S
b11111010000 T
b11000011010100000 Y
b11111010 Z
r10 #
b0 @
b0 c
1'
1(
0/
1.
0-
0,
1+
0*
0)
03
12
11
10
09
08
07
06
0\
0[
0V
0U
0K
0J
$end
#5000
1$
16
#10000
0$
06
#15000
1$
16
#20000
0$
06
#25000
1$
16
#30000
0$
06
#35000
1$
16
#40000
0$
06
#45000
1$
16
#50000
0$
06
#55000
1$
16
#60000
0$
06
#65000
1$
16
#70000
0$
06
#75000
1$
16
#80000
0$
06
#85000
1$
16
#90000
0$
06
#95000
1$
16
1%
17
#100000
0$
06
#105000
1$
16
b1 M
b1 X
b1 c
#110000
0$
06
#115000
1$
16
b10 M
b10 X
b10 c
#120000
0$
06
#125000
1$
16
b11 M
b11 X
b11 c
#130000
0$
06
#135000
1$
16
b100 M
b100 X
b100 c
#140000
0$
06
#145000
1$
16
b101 M
b101 X
b101 c
#150000
0$
06
#155000
1$
16
b110 M
b110 X
b110 c
#160000
0$
06
#165000
1$
16
b111 M
b111 X
b111 c
#170000
0$
06
#175000
1$
16
b1000 M
b1000 X
b1000 c
#180000
0$
06
#185000
1$
16
b1001 M
b1001 X
b1001 c
#190000
0$
06
#195000
1$
16
b1010 M
b1010 X
b1010 c
#200000
0$
06
#205000
1$
16
b1011 M
b1011 X
b1011 c
#210000
0$
06
#215000
1$
16
b1100 M
b1100 X
b1100 c
#220000
0$
06
#225000
1$
16
b1101 M
b1101 X
b1101 c
#230000
0$
06
#235000
1$
16
b1110 M
b1110 X
b1110 c
#240000
0$
06
#245000
1$
16
b1111 M
b1111 X
b1111 c
#250000
0$
06
#255000
1$
16
b10000 M
b10000 X
b10000 c
#260000
0$
06
#265000
1$
16
b10001 M
b10001 X
b10001 c
#270000
0$
06
#275000
1$
16
b10010 M
b10010 X
b10010 c
#280000
0$
06
#285000
1$
16
b10011 M
b10011 X
b10011 c
#290000
0$
06
#295000
1$
16
b10100 M
b10100 X
b10100 c
#300000
0$
06
#305000
1$
16
b10101 M
b10101 X
b10101 c
#310000
0$
06
#315000
1$
16
b10110 M
b10110 X
b10110 c
#320000
0$
06
#325000
1$
16
b10111 M
b10111 X
b10111 c
#330000
0$
06
#335000
1$
16
b11000 M
b11000 X
b11000 c
#340000
0$
06
#345000
1$
16
b11001 M
b11001 X
b11001 c
#350000
0$
06
#355000
1$
16
b11010 M
b11010 X
b11010 c
#360000
0$
06
#365000
1$
16
b11011 M
b11011 X
b11011 c
#370000
0$
06
#375000
1$
16
b11100 M
b11100 X
b11100 c
#380000
0$
06
#385000
1$
16
b11101 M
b11101 X
b11101 c
#390000
0$
06
#395000
1$
16
b11110 M
b11110 X
b11110 c
#400000
0$
06
#405000
1$
16
b11111 M
b11111 X
b11111 c
#410000
0$
06
#415000
1$
16
b100000 M
b100000 X
b100000 c
#420000
0$
06
#425000
1$
16
b100001 M
b100001 X
b100001 c
#430000
0$
06
#435000
1$
16
b100010 M
b100010 X
b100010 c
#440000
0$
06
#445000
1$
16
b100011 M
b100011 X
b100011 c
#450000
0$
06
#455000
1$
16
b100100 M
b100100 X
b100100 c
#460000
0$
06
#465000
1$
16
b100101 M
b100101 X
b100101 c
#470000
0$
06
#475000
1$
16
b100110 M
b100110 X
b100110 c
#480000
0$
06
#485000
1$
16
b100111 M
b100111 X
b100111 c
#490000
0$
06
#495000
1$
16
b101000 M
b101000 X
b101000 c
#500000
0$
06
#505000
1$
16
b101001 M
b101001 X
b101001 c
#510000
0$
06
#515000
1$
16
b101010 M
b101010 X
b101010 c
#520000
0$
06
#525000
1$
16
b101011 M
b101011 X
b101011 c
#530000
0$
06
#535000
1$
16
b101100 M
b101100 X
b101100 c
#540000
0$
06
#545000
1$
16
b101101 M
b101101 X
b101101 c
#550000
0$
06
#555000
1$
16
b101110 M
b101110 X
b101110 c
#560000
0$
06
#565000
1$
16
b101111 M
b101111 X
b101111 c
#570000
0$
06
#575000
1$
16
b110000 M
b110000 X
b110000 c
#580000
0$
06
#585000
1$
16
b110001 M
b110001 X
b110001 c
#590000
0$
06
#595000
1$
16
b110010 M
b110010 X
b110010 c
#600000
0$
06
#605000
1$
16
b110011 M
b110011 X
b110011 c
#610000
0$
06
#615000
1$
16
b110100 M
b110100 X
b110100 c
#620000
0$
06
#625000
1$
16
b110101 M
b110101 X
b110101 c
#630000
0$
06
#635000
1$
16
b110110 M
b110110 X
b110110 c
#640000
0$
06
#645000
1$
16
b110111 M
b110111 X
b110111 c
#650000
0$
06
#655000
1$
16
b111000 M
b111000 X
b111000 c
#660000
0$
06
#665000
1$
16
b111001 M
b111001 X
b111001 c
#670000
0$
06
#675000
1$
16
b111010 M
b111010 X
b111010 c
#680000
0$
06
#685000
1$
16
b111011 M
b111011 X
b111011 c
#690000
0$
06
#695000
1$
16
b111100 M
b111100 X
b111100 c
#700000
0$
06
#705000
1$
16
b111101 M
b111101 X
b111101 c
#710000
0$
06
#715000
1$
16
b111110 M
b111110 X
b111110 c
#720000
0$
06
#725000
1$
16
b111111 M
b111111 X
b111111 c
#730000
0$
06
#735000
1$
16
b1000000 M
b1000000 X
b1000000 c
#740000
0$
06
#745000
1$
16
b1000001 M
b1000001 X
b1000001 c
#750000
0$
06
#755000
1$
16
b1000010 M
b1000010 X
b1000010 c
#760000
0$
06
#765000
1$
16
b1000011 M
b1000011 X
b1000011 c
#770000
0$
06
#775000
1$
16
b1000100 M
b1000100 X
b1000100 c
#780000
0$
06
#785000
1$
16
b1000101 M
b1000101 X
b1000101 c
#790000
0$
06
#795000
1$
16
b1000110 M
b1000110 X
b1000110 c
#800000
0$
06
#805000
1$
16
b1000111 M
b1000111 X
b1000111 c
#810000
0$
06
#815000
1$
16
b1001000 M
b1001000 X
b1001000 c
#820000
0$
06
#825000
1$
16
b1001001 M
b1001001 X
b1001001 c
#830000
0$
06
#835000
1$
16
b1001010 M
b1001010 X
b1001010 c
#840000
0$
06
#845000
1$
16
b1001011 M
b1001011 X
b1001011 c
#850000
0$
06
#855000
1$
16
b1001100 M
b1001100 X
b1001100 c
#860000
0$
06
#865000
1$
16
b1001101 M
b1001101 X
b1001101 c
#870000
0$
06
#875000
1$
16
b1001110 M
b1001110 X
b1001110 c
#880000
0$
06
#885000
1$
16
b1001111 M
b1001111 X
b1001111 c
#890000
0$
06
#895000
1$
16
b1010000 M
b1010000 X
b1010000 c
#900000
0$
06
#905000
1$
16
b1010001 M
b1010001 X
b1010001 c
#910000
0$
06
#915000
1$
16
b1010010 M
b1010010 X
b1010010 c
#920000
0$
06
#925000
1$
16
b1010011 M
b1010011 X
b1010011 c
#930000
0$
06
#935000
1$
16
b1010100 M
b1010100 X
b1010100 c
#940000
0$
06
#945000
1$
16
b1010101 M
b1010101 X
b1010101 c
#950000
0$
06
